Workbook

Sheet Leia-me
A1: Banco de dados do Encaminha Goiânia
A3: Para que serve | B3: Guarda os dados do app fora dele: serviços e contatos da rede, textos das políticas, temas do pedido livre e os atendimentos registrados de forma anônima. A equipe gestora atualiza aqui; o app lê daqui.
A4: Serviços | B4: Um serviço por linha. Atualize telefone, endereço, horário e observação. Ao conferir, mude a Situação e preencha Conferido em e Conferido por. A coluna Precisa conferir? avisa sozinha: Sim quando nunca foi conferido ou passou de 180 dias.
A5: Políticas | B5: Nome, valor, passo a passo e documentos de cada política. Uma linha do passo a passo por linha da célula. Quem tem direito (o critério) fica no código do app e é testado; para mudar um critério, escreva o pedido na coluna Mudança de critério pedida.
A6: Temas | B6: Situações que o app reconhece no pedido livre. Palavras-chave sem acento, separadas por vírgula. Uma palavra curta (até 3 letras) precisa aparecer inteira; as demais valem no começo de uma palavra.
A7: Registros | B7: Preenchida pelo app quando o profissional toca em Registrar atendimento. Não edite à mão. Só dados anônimos: nada de nome, iniciais, texto livre, renda ou idade exatas.
A8: Resumo | B8: Contagens por fórmula sobre a aba Registros. Atualiza sozinha quando chegam registros.
A9: Fontes | B9: De onde veio cada tabela e quando foi exportada.
A10: Como editar | B10: Não mude a coluna ID nem a ordem das colunas: o app usa os IDs para ligar políticas, temas e serviços. Para incluir um serviço novo, use uma linha nova no fim, com um ID novo, curto e sem espaço (ex.: caps-ad-leste).
A11: Legenda | B11: Células em amarelo claro: colunas de conferência que a equipe preenche.
A12: LGPD | B12: Nunca registre nome, CPF, NIS, endereço, telefone ou e-mail de pessoa atendida. Raça, religião, orientação sexual e dados de saúde de uma pessoa identificável são dados sensíveis. Os registros do app são anônimos e situações sensíveis com 1 ou 2 casos não devem ser divulgadas.
A13: Acesso | B13: Edição só para a equipe gestora. Para profissionais que só consultam, compartilhe como Leitor.

Sheet Serviços
A1: ID (não altere) | B1: Nome | C1: Tipo | D1: Município | E1: Região de Goiânia | F1: Endereço | G1: Telefones (separe com /) | H1: E-mail | I1: Horário | J1: Site | K1: Observação | L1: Fonte | M1: Situação | N1: Conferido em | O1: Conferido por (setor) | P1: Precisa conferir?
A2: mxc | B2: Unidade de Integração e Referência Social Maria Xavier Caiado | C2: Estadual (Seds) | D2: Estado | F2: Av. Anhanguera, 3463, Setor Leste Universitário, Goiânia, CEP 74610-010 | G2: (62) 3270-9610 | I2: Seg a sex, 8h às 17h | K2: Entrega e 2ª via dos cartões Mães de Goiás, Dignidade e Goiás + Inclusivo. CIPTEA, Passe Livre PcD e Passaporte da Pessoa Idosa. | L2: Protótipo do app (ver aba Fontes) | M2: Ativo | P2: =IF($A2="","",IF($M2="Inativo","Não",IF($N2="","Sim",IF(TODAY()-$N2>180,"Sim","Não"))))
A3: seds | B3: Seds, Secretaria de Estado de Desenvolvimento Social | C3: Estadual (Seds) | D3: Estado | F3: Praça Dr. Pedro Ludovico Teixeira, 332, Blocos A a D, Setor Central, Goiânia, CEP 74003-010 | G3: (62) 3270-9603 / Ouvidoria (62) 3270-9604 | H3: ouvidoria.seds@goias.gov.br | I3: Seg a sex, 8h às 18h | L3: Protótipo do app (ver aba Fontes) | M3: Ativo | P3: =IF($A3="","",IF($M3="Inativo","Não",IF($N3="","Sim",IF(TODAY()-$N3>180,"Sim","Não"))))
A4: pcd | B4: Gerência da Pessoa com Deficiência (Seds) | C4: Estadual (Seds) | D4: Estado | F4: Av. Anhanguera, 3463, Setor Leste Universitário, Goiânia, CEP 74610-010 | G4: (62) 3270-9620 / WhatsApp (62) 98104-3652 | H4: pcd@goias.gov.br | I4: Seg a sex, 7h30 às 18h | L4: Protótipo do app (ver aba Fontes) | M4: Ativo | P4: =IF($A4="","",IF($M4="Inativo","Não",IF($N4="","Sim",IF(TODAY()-$N4>180,"Sim","Não"))))
A5: passaporte | B5: Passaporte da Pessoa Idosa (Seds) | C5: Estadual (Seds) | D5: Estado | F5: Av. Anhanguera, 3463, Setor Leste Universitário, Goiânia, CEP 74610-010 | G5: (62) 3270-9621 / (62) 98306-0327 | H5: passaporte.seds@goias.gov.br | I5: Seg a sex, 7h às 17h30 | L5: Protótipo do app (ver aba Fontes) | M5: Ativo | P5: =IF($A5="","",IF($M5="Inativo","Não",IF($N5="","Sim",IF(TODAY()-$N5>180,"Sim","Não"))))
A6: mulherseds | B6: Superintendência da Mulher (Seds), Goiás Por Elas | C6: Estadual (Seds) | D6: Estado | F6: Praça Dr. Pedro Ludovico Teixeira, 332, Bloco B, térreo, Setor Central, Goiânia | G6: WhatsApp (62) 98270-0214 | H6: crei.seds@goias.gov.br | L6: Protótipo do app (ver aba Fontes) | M6: Ativo | P6: =IF($A6="","",IF($M6="Inativo","Não",IF($N6="","Sim",IF(TODAY()-$N6>180,"Sim","Não"))))
A7: juventude | B7: Passe Livre Estudantil (Seds) | C7: Estadual (Seds) | D7: Estado | F7: Praça Dr. Pedro Ludovico Teixeira, 332, Bloco C, térreo, Setor Central, Goiânia, CEP 74083-010 | G7: (62) 3270-9624 / WhatsApp (62) 98306-0294 / RedeMob 0800 648 2222 | H7: passelivre@goias.gov.br | J7: https://www.juventude.go.gov.br/ | L7: Protótipo do app (ver aba Fontes) | M7: Ativo | P7: =IF($A7="","",IF($M7="Inativo","Não",IF($N7="","Sim",IF(TODAY()-$N7>180,"Sim","Não"))))
A8: registro | B8: Registro Civil, 2ª via gratuita (Seds) | C8: Estadual (Seds) | D8: Estado | F8: Av. Anhanguera, 3463, Setor Leste Universitário, Goiânia, CEP 74610-010 | G8: WhatsApp (62) 3270-9644 | H8: garantiadedireitos.seds@goias.gov.br | L8: Protótipo do app (ver aba Fontes) | M8: Ativo | P8: =IF($A8="","",IF($M8="Inativo","Não",IF($N8="","Sim",IF(TODAY()-$N8>180,"Sim","Não"))))
A9: agehab | B9: Agehab, Agência Goiana de Habitação | C9: Estadual (Agehab) | D9: Estado | F9: Rua 18-A, nº 541, Setor Aeroporto, Goiânia, CEP 74070-060 | G9: (62) 3096-5005 / (62) 3096-5050 | I9: 8h às 17h | J9: https://aluguelsocial.agehab.go.gov.br | L9: Protótipo do app (ver aba Fontes) | M9: Ativo | P9: =IF($A9="","",IF($M9="Inativo","Não",IF($N9="","Sim",IF(TODAY()-$N9>180,"Sim","Não"))))
A10: aprendiz | B10: Aprendiz do Futuro | C10: Estadual (Seds) | D10: Estado | G10: 0800 494 1052 | J10: https://aprendizdofuturo.org.br | L10: Protótipo do app (ver aba Fontes) | M10: Ativo | P10: =IF($A10="","",IF($M10="Inativo","Não",IF($N10="","Sim",IF(TODAY()-$N10>180,"Sim","Não"))))
A11: 121 | B11: Disque Social 121 (MDS) | C11: Nacional | D11: Nacional | G11: 121 | K11: Bolsa Família, Cadastro Único e endereço do CRAS mais próximo. | L11: Protótipo do app (ver aba Fontes) | M11: Ativo | P11: =IF($A11="","",IF($M11="Inativo","Não",IF($N11="","Sim",IF(TODAY()-$N11>180,"Sim","Não"))))
A12: 135 | B12: INSS, Central 135 e Meu INSS | C12: Nacional | D12: Nacional | G12: 135 | J12: https://meu.inss.gov.br | K12: Pedido de BPC, agendamento de perícia e avaliação social. | L12: Protótipo do app (ver aba Fontes) | M12: Ativo | P12: =IF($A12="","",IF($M12="Inativo","Não",IF($N12="","Sim",IF(TODAY()-$N12>180,"Sim","Não"))))
A13: 100 | B13: Disque 100, Direitos Humanos | C13: Nacional | D13: Nacional | G13: 100 | K13: Denúncia anônima de violência contra criança, idoso, pessoa com deficiência, população de rua e LGBTQIA+, tráfico de pessoas e trabalho escravo. 24h. Também por WhatsApp (61) 99611-0100. | L13: Protótipo do app (ver aba Fontes) | M13: Ativo | P13: =IF($A13="","",IF($M13="Inativo","Não",IF($N13="","Sim",IF(TODAY()-$N13>180,"Sim","Não"))))
A14: 180 | B14: Ligue 180, Central de Atendimento à Mulher | C14: Nacional | D14: Nacional | G14: 180 | K14: Gratuito, sigiloso, 24h. | L14: Protótipo do app (ver aba Fontes) | M14: Ativo | P14: =IF($A14="","",IF($M14="Inativo","Não",IF($N14="","Sim",IF(TODAY()-$N14>180,"Sim","Não"))))
A15: 188 | B15: CVV, Centro de Valorização da Vida | C15: Nacional | D15: Nacional | G15: 188 | I15: Telefone 24h, todos os dias | J15: https://cvv.org.br | K15: Apoio emocional e prevenção do suicídio. Ligação gratuita e sigilosa, de qualquer telefone. Também há chat em cvv.org.br, em horários limitados: confira no site. | L15: Protótipo do app (ver aba Fontes) | M15: Ativo | P15: =IF($A15="","",IF($M15="Inativo","Não",IF($N15="","Sim",IF(TODAY()-$N15>180,"Sim","Não"))))
A16: ciatox | B16: CIATox Goiás, Centro de Informação e Assistência Toxicológica | C16: Saúde | D16: Estado | G16: 0800 646 4350 | I16: 24h, todos os dias | J16: https://goias.gov.br/saude/ciatox/ | K16: Orienta profissionais e população em intoxicação por remédio, veneno, agrotóxico, produto de limpeza ou animal peçonhento. Fonte: SES/GO, consultado em 08/10/2026. | L16: SES/GO, consultado em 08/10/2026 | M16: Ativo | N16: 46303 | O16: Levantamento de 08/10/2026 | P16: =IF($A16="","",IF($M16="Inativo","Não",IF($N16="","Sim",IF(TODAY()-$N16>180,"Sim","Não"))))
A17: crer | B17: CRER, Centro Estadual de Reabilitação e Readaptação Dr. Henrique Santillo | C17: Saúde | D17: Estado | F17: Av. Vereador José Monteiro, 1655, Setor Negrão de Lima, Goiânia, CEP 74653-230 | G17: Recepção (62) 3232-3232 / (62) 3232-3000 | J17: https://goias.gov.br/saude/crer/ | K17: Reabilitação pelo SUS. A primeira consulta é agendada pela regulação, com encaminhamento da UBS; não há procura direta. Fonte: SES/GO, consultado em 08/10/2026. | L17: SES/GO, consultado em 08/10/2026 | M17: Ativo | N17: 46303 | O17: Levantamento de 08/10/2026 | P17: =IF($A17="","",IF($M17="Inativo","Não",IF($N17="","Sim",IF(TODAY()-$N17>180,"Sim","Não"))))
A18: credeq | B18: Credeq Prof. Jamil Issy, referência estadual em dependência química | C18: Saúde | D18: Aparecida de Goiânia | K18: Casos graves de álcool e drogas, com internação voluntária de até 90 dias. A vaga vem pela regulação, com encaminhamento do CAPS AD. Fonte: Governo de Goiás e imprensa; endereço e telefone ainda não conferidos. | L18: Governo de Goiás e imprensa; endereço e telefone ainda não conferidos | M18: A conferir | P18: =IF($A18="","",IF($M18="Inativo","Não",IF($N18="","Sim",IF(TODAY()-$N18>180,"Sim","Não"))))
A19: autoexclusao | B19: Autoexclusão de apostas (Ministério da Fazenda) | C19: Nacional | D19: Nacional | J19: https://www.gov.br/pt-br/servicos/plataforma-centralizada-de-autoexclusao-apostas | K19: Bloqueia o CPF em todas as bets autorizadas, de 1 a 12 meses ou por tempo indeterminado, e corta a publicidade. Exige conta gov.br prata ou ouro. Fonte: gov.br, consultado em 08/10/2026. | L19: gov.br, consultado em 08/10/2026 | M19: Ativo | N19: 46303 | O19: Levantamento de 08/10/2026 | P19: =IF($A19="","",IF($M19="Inativo","Não",IF($N19="","Sim",IF(TODAY()-$N19>180,"Sim","Não"))))
A20: sine | B20: Sine Goiânia | C20: Trabalho | D20: Goiânia | F20: Rua 1, nº 147, Setor Central, Goiânia | K20: Vagas, seguro-desemprego e orientação profissional. Agendamento pelo app Prefeitura 24h. Levar RG, CPF, carteira de trabalho e comprovante de endereço. Endereço de reportagem recente: confirme antes de ir. | L20: Protótipo do app (ver aba Fontes) | M20: A conferir | P20: =IF($A20="","",IF($M20="Inativo","Não",IF($N20="","Sim",IF(TODAY()-$N20>180,"Sim","Não"))))
A21: procon | B21: Procon Goiás | C21: Justiça e direitos | D21: Estado | F21: Rua 8, nº 242, Setor Central, Goiânia | G21: Goiânia 151 / Interior (62) 3201-7124 / Superendividados (62) 3201-2891 | I21: Seg a sex, 8h às 17h | J21: https://www.procon.go.gov.br | K21: Reclamação de consumo, juros abusivos e renegociação de dívidas (Núcleo de Apoio aos Superendividados). Fonte: Procon Goiás, 2022: confirme os telefones. | L21: Procon Goiás, 2022: confirme os telefones | M21: A conferir | P21: =IF($A21="","",IF($M21="Inativo","Não",IF($N21="","Sim",IF(TODAY()-$N21>180,"Sim","Não"))))
A22: pc197 | B22: Disque Polícia Civil 197 | C22: Justiça e direitos | D22: Estado | G22: 197 | I22: 24h | K22: Orientação e denúncia à Polícia Civil de Goiás. | L22: Protótipo do app (ver aba Fontes) | M22: Ativo | P22: =IF($A22="","",IF($M22="Inativo","Não",IF($N22="","Sim",IF(TODAY()-$N22>180,"Sim","Não"))))
A23: dpca | B23: DPCA, Delegacia de Proteção à Criança e ao Adolescente | C23: Justiça e direitos | D23: Goiânia | F23: Rua C-190 esq. c/ C-107, Qd. 226, Lt. 13, Jardim América, Goiânia, CEP 74255-080 | G23: (62) 3286-1540 / (62) 3286-1298 / (62) 3286-1552 | H23: dpca.goiania.pcgo@pc.goias.gov.br | I23: Seg a sex, 8h às 12h e 14h às 18h | K23: Crimes contra crianças e adolescentes, inclusive violência sexual. Fonte: Polícia Civil de Goiás, consultado em 08/10/2026. | L23: Polícia Civil de Goiás, consultado em 08/10/2026 | M23: Ativo | N23: 46303 | O23: Levantamento de 08/10/2026 | P23: =IF($A23="","",IF($M23="Inativo","Não",IF($N23="","Sim",IF(TODAY()-$N23>180,"Sim","Não"))))
A24: deacri | B24: Deacri, Delegacia de Crimes Raciais e de Intolerância | C24: Justiça e direitos | D24: Goiânia | F24: Av. 2ª Radial, Qd. 48, Lt. 28, Setor Pedro Ludovico, Goiânia, CEP 74820-090 | G24: (62) 98495-2047 | H24: deacri.pcgo@pc.goias.gov.br | I24: Seg a sex, 8h às 18h | K24: Racismo, injúria racial, xenofobia, intolerância religiosa e LGBTfobia, inclusive ataques a terreiros. Também é possível registrar em qualquer delegacia ou pelo 197. Fonte: Polícia Civil de Goiás, consultado em 08/10/2026. | L24: Polícia Civil de Goiás, consultado em 08/10/2026 | M24: Ativo | N24: 46303 | O24: Levantamento de 08/10/2026 | P24: =IF($A24="","",IF($M24="Inativo","Não",IF($N24="","Sim",IF(TODAY()-$N24>180,"Sim","Não"))))
A25: crei | B25: Crei, Centro de Referência Estadual da Igualdade (Seds) | C25: Justiça e direitos | D25: Estado | H25: crei.seds@goias.gov.br | J25: https://goias.gov.br/social/superintendencia-da-igualdade-racial/ | K25: Atendimento psicológico, social e jurídico gratuito, presencial e on-line, a vítimas de racismo, intolerância religiosa e outras discriminações. Ligado à Superintendência da Igualdade Racial, que tem gerência para povos de terreiro. Fonte: Seds/GO; o e-mail aparece também na Superintendência da Mulher: confirme. | L25: Seds/GO; o e-mail aparece também na Superintendência da Mulher: confirme | M25: A conferir | P25: =IF($A25="","",IF($M25="Inativo","Não",IF($N25="","Sim",IF(TODAY()-$N25>180,"Sim","Não"))))
A26: deai | B26: Delegacia Estadual de Atendimento ao Idoso | C26: Justiça e direitos | D26: Goiânia | F26: Av. Anhanguera, nº 463, Setor Universitário, Goiânia | G26: (62) 3201-1501 / (62) 3201-1511 | I26: 8h às 18h | K26: Crimes contra a pessoa idosa. Dados da inauguração (2016): confirme antes de ir ou use o 197. | L26: Protótipo do app (ver aba Fontes) | M26: A conferir | P26: =IF($A26="","",IF($M26="Inativo","Não",IF($N26="","Sim",IF(TODAY()-$N26>180,"Sim","Não"))))
A27: hc-ufg | B27: Hospital das Clínicas da UFG (Ebserh) | C27: Saúde | D27: Goiânia | G27: (62) 3269-8380 | J27: https://www.gov.br/ebserh/pt-br/hospitais-universitarios/regiao-centro-oeste/hc-ufg | K27: Hospital-escola 100% SUS. Consultas e cirurgias pela regulação, com encaminhamento da UBS. Telefone de 2021: confirme. Carta de Serviços 2026 no site. | L27: Protótipo do app (ver aba Fontes) | M27: A conferir | P27: =IF($A27="","",IF($M27="Inativo","Não",IF($N27="","Sim",IF(TODAY()-$N27>180,"Sim","Não"))))
A28: araujo-jorge | B28: Hospital de Câncer Araújo Jorge (ACCG) | C28: Saúde | D28: Goiânia | J28: https://www.accg.org.br | K28: Único Centro de Alta Complexidade em Oncologia (Cacon) do Estado, filantrópico com atendimento SUS. Acesso pela regulação. Houve suspensões de novos atendimentos em 2025: confirme antes. | L28: Protótipo do app (ver aba Fontes) | M28: A conferir | P28: =IF($A28="","",IF($M28="Inativo","Não",IF($N28="","Sim",IF(TODAY()-$N28>180,"Sim","Não"))))
A29: capsi | B29: CAPSi estadual, saúde mental de crianças e adolescentes | C29: Saúde | D29: Goiânia | F29: Rua 72 c/ Av. H, s/n, Parque da Criança, Jardim Goiás, Goiânia, CEP 74805-480 | G29: (62) 3201-4346 / (62) 3201-4473 | H29: capsiestadual@gmail.com | K29: De 3 a 17 anos, com os pais ou responsáveis: psicologia, fonoaudiologia, terapia ocupacional, grupos e serviço social. Fonte: SES/GO; confirme o horário por telefone. | L29: SES/GO; confirme o horário por telefone | M29: A conferir | P29: =IF($A29="","",IF($M29="Inativo","Não",IF($N29="","Sim",IF(TODAY()-$N29>180,"Sim","Não"))))
A30: hgg-tx | B30: Ambulatório TX do HGG, saúde da pessoa trans | C30: Saúde | D30: Goiânia | J30: https://goias.gov.br/saude/ambulatorio-para-transexuais-comeca-a-funcionar-no-hgg/ | K30: Hormonização, psicologia, fonoaudiologia e cirurgias pelo SUS. Entrada com encaminhamento da UBS. Fonte: SES/GO. | L30: SES/GO | M30: Ativo | P30: =IF($A30="","",IF($M30="Inativo","Não",IF($N30="","Sim",IF(TODAY()-$N30>180,"Sim","Não"))))
A31: transviver | B31: Ambulatório Transviver (Prefeitura de Goiânia) | C31: Saúde | D31: Goiânia | F31: Nas instalações da UPA Novo Mundo, Goiânia | I31: Seg a sex, 7h às 19h | K31: Para maiores de 18 anos: endocrinologia, psicologia, enfermagem, serviço social e hormônios. Fonte: imprensa, 2024: confirme. | L31: imprensa, 2024: confirme | M31: A conferir | P31: =IF($A31="","",IF($M31="Inativo","Não",IF($N31="","Sim",IF(TODAY()-$N31>180,"Sim","Não"))))
A32: escritorio-social | B32: Escritório Social, apoio a egressos do sistema prisional | C32: Justiça e direitos | D32: Goiânia | F32: Rua 83, nº 484, Setor Sul, Goiânia | K32: Egressos, pré-egressos e liberados condicionais e suas famílias: documentos, trabalho, estudo e políticas sociais. Atendimento voluntário. Inaugurado em dez/2024 (Goiás Social): confirme o horário. | L32: Protótipo do app (ver aba Fontes) | M32: A conferir | P32: =IF($A32="","",IF($M32="Inativo","Não",IF($N32="","Sim",IF(TODAY()-$N32>180,"Sim","Não"))))
A33: pastoral-migrantes | B33: Pastoral dos Migrantes de Goiânia | C33: Rede comunitária e gratuita | D33: Goiânia | G33: (62) 4018-1606 / (62) 99635-1212 | K33: Acolhe migrantes e refugiados (venezuelanos, haitianos e outros): orientação, documentos, trabalho. Tem ponto de atendimento na rodoviária. Fonte: CSEM, publicação antiga: confirme. | L33: CSEM, publicação antiga: confirme | M33: A conferir | P33: =IF($A33="","",IF($M33="Inativo","Não",IF($N33="","Sim",IF(TODAY()-$N33>180,"Sim","Não"))))
A34: cejusc | B34: Cejusc, conciliação gratuita do TJGO | C34: Justiça e direitos | D34: Goiânia | F34: Fórum Cível de Goiânia, Av. Olinda c/ Rua PL-03, Park Lozandes | G34: WhatsApp (62) 99218-2532 | K34: Acordo sobre pensão, guarda, visitas, divórcio e dívidas, sem processo. WhatsApp divulgado nas Semanas da Conciliação de 2023 e 2024: confirme. | L34: Protótipo do app (ver aba Fontes) | M34: A conferir | P34: =IF($A34="","",IF($M34="Inativo","Não",IF($N34="","Sim",IF(TODAY()-$N34>180,"Sim","Não"))))
A35: restbem | B35: Restaurante do Bem (OVG), refeição a R$ 2 | C35: Rede comunitária e gratuita | D35: Goiânia | F35: Av. Araguaia esq. c/ Rua 3, nº 514, Setor Central, Goiânia | J35: https://ovg.org.br | K35: Almoço a R$ 2 para pessoas em vulnerabilidade, idosos e população de rua. Há outras unidades em Goiânia (Campinas) e no interior. Fonte: regulamento OVG, 2024: confirme o horário. | L35: regulamento OVG, 2024: confirme o horário | M35: A conferir | P35: =IF($A35="","",IF($M35="Inativo","Não",IF($N35="","Sim",IF(TODAY()-$N35>180,"Sim","Não"))))
A36: bancoalimentos | B36: Banco de Alimentos da OVG (para entidades) | C36: Rede comunitária e gratuita | D36: Estado | J36: https://ovg.org.br | K36: Entidades sem fins lucrativos que servem refeições se cadastram pelo site da OVG e recebem alimentos da Ceasa. Útil para igrejas e ONGs da rede. | L36: Protótipo do app (ver aba Fontes) | M36: Ativo | P36: =IF($A36="","",IF($M36="Inativo","Não",IF($N36="","Sim",IF(TODAY()-$N36>180,"Sim","Não"))))
A37: pestalozzi | B37: Associação Pestalozzi de Goiânia | C37: Rede comunitária e gratuita | D37: Goiânia | F37: Centro Peter Pan: Praça da Bíblia, Qd. K, Vila Santa Isabel, Goiânia | K37: Atendimento especializado e educação para pessoas com deficiência intelectual ou múltipla. Fonte: convênio com a Seduc/GO: confirme. | L37: convênio com a Seduc/GO: confirme | M37: A conferir | P37: =IF($A37="","",IF($M37="Inativo","Não",IF($N37="","Sim",IF(TODAY()-$N37>180,"Sim","Não"))))
A38: apae-gyn | B38: APAE de Goiânia | C38: Rede comunitária e gratuita | D38: Goiânia | F38: Rua 255, nº 628, Setor Coimbra, Goiânia | K38: Pessoas com deficiência intelectual ou múltipla: pediatria, psicologia, neurologia, fisioterapia, odontologia. Fonte: diretório não oficial: confirme. | L38: diretório não oficial: confirme | M38: A conferir | P38: =IF($A38="","",IF($M38="Inativo","Não",IF($N38="","Sim",IF(TODAY()-$N38>180,"Sim","Não"))))
A39: anhanguera-psi | B39: Clínica-escola de Psicologia da Faculdade Anhanguera de Goiânia | C39: Rede comunitária e gratuita | D39: Goiânia | K39: Psicoterapia, orientação e avaliação psicológica para crianças, adolescentes, adultos e idosos, por alunos supervisionados. Fonte: imprensa, 2025: confirme como agendar. | L39: imprensa, 2025: confirme como agendar | M39: A conferir | P39: =IF($A39="","",IF($M39="Inativo","Não",IF($N39="","Sim",IF(TODAY()-$N39>180,"Sim","Não"))))
A40: mec | B40: MEC: Prouni, Fies e Sisu | C40: Educação | D40: Nacional | G40: Fale Conosco 0800 616161 | J40: https://acessounico.mec.gov.br | K40: Inscrições com a conta gov.br, nas datas de cada edital. Prouni e Fies abrem duas vezes por ano; o Sisu, no início do ano. | L40: Protótipo do app (ver aba Fontes) | M40: Ativo | P40: =IF($A40="","",IF($M40="Inativo","Não",IF($N40="","Sim",IF(TODAY()-$N40>180,"Sim","Não"))))
A41: inep | B41: Inep: Enem e Encceja | C41: Educação | D41: Nacional | J41: https://www.gov.br/inep | K41: Isenção da taxa do Enem (em abril), inscrições e Encceja, na Página do Participante, com a conta gov.br. | L41: Protótipo do app (ver aba Fontes) | M41: Ativo | P41: =IF($A41="","",IF($M41="Inativo","Não",IF($N41="","Sim",IF(TODAY()-$N41>180,"Sim","Não"))))
A42: ovg | B42: ProBem, OVG (bolsas universitárias do Estado) | C42: Educação | D42: Estado | G42: Região metropolitana (62) 3270-8500 / Interior 0800 062 9413 / WhatsApp (62) 99641-6090 | J42: https://www.ovg.org.br | K42: Inscrições por edital, uma vez por semestre, só pelo site da OVG. Seleção pelo CadÚnico. Fonte: Governo de Goiás e imprensa, 2026. | L42: Governo de Goiás e imprensa, 2026 | M42: Ativo | P42: =IF($A42="","",IF($M42="Inativo","Não",IF($N42="","Sim",IF(TODAY()-$N42>180,"Sim","Não"))))
A43: samu | B43: SAMU 192 | C43: Saúde | D43: Região metropolitana | G43: 192 | K43: Emergência com risco de vida. A Central de Regulação de Goiânia atende a região metropolitana. | L43: Protótipo do app (ver aba Fontes) | M43: Ativo | P43: =IF($A43="","",IF($M43="Inativo","Não",IF($N43="","Sim",IF(TODAY()-$N43>180,"Sim","Não"))))
A44: hugo | B44: HUGO, Hospital Estadual de Urgências de Goiânia | C44: Saúde | D44: Goiânia | G44: (62) 3201-4420 | L44: Protótipo do app (ver aba Fontes) | M44: Ativo | P44: =IF($A44="","",IF($M44="Inativo","Não",IF($N44="","Sim",IF(TODAY()-$N44>180,"Sim","Não"))))
A45: hmi | B45: HMI, Hospital Estadual Materno-Infantil | C45: Saúde | D45: Goiânia | G45: (62) 3956-2900 | L45: Protótipo do app (ver aba Fontes) | M45: Ativo | P45: =IF($A45="","",IF($M45="Inativo","Não",IF($N45="","Sim",IF(TODAY()-$N45>180,"Sim","Não"))))
A46: hem | B46: Hemu, Hospital Estadual da Mulher | C46: Saúde | D46: Goiânia | G46: (62) 3956-2901 | J46: https://goias.gov.br/saude/hemu/ | K46: Ambulatório de Atendimento às Vítimas de Violência Sexual (mulheres, homens, adolescentes e crianças), por procura direta ou encaminhamento: contracepção de emergência, profilaxia de IST e HIV, psicologia. Referência estadual para o aborto previsto em lei. | L46: Protótipo do app (ver aba Fontes) | M46: Ativo | P46: =IF($A46="","",IF($M46="Inativo","Não",IF($N46="","Sim",IF(TODAY()-$N46>180,"Sim","Não"))))
A47: huapa | B47: Huapa, Hospital Estadual de Aparecida | C47: Saúde | D47: Aparecida de Goiânia | G47: (62) 3217-8900 | L47: Protótipo do app (ver aba Fontes) | M47: Ativo | P47: =IF($A47="","",IF($M47="Inativo","Não",IF($N47="","Sim",IF(TODAY()-$N47>180,"Sim","Não"))))
A48: hutrin | B48: Hutrin, Hospital Estadual de Trindade | C48: Saúde | D48: Trindade | G48: (62) 3506-7002 | L48: Protótipo do app (ver aba Fontes) | M48: Ativo | P48: =IF($A48="","",IF($M48="Inativo","Não",IF($N48="","Sim",IF(TODAY()-$N48>180,"Sim","Não"))))
A49: cemac | B49: Cemac Juarez Barbosa, Centro Estadual de Medicação de Alto Custo | C49: Saúde | D49: Estado | F49: Rua 16, nº 97, Setor Central, Goiânia, CEP 74015-020 | G49: (62) 3201-7446 / (62) 3201-7450 / Dúvidas/WhatsApp (62) 3201-7453 | I49: Seg a sex, 7h às 17h | J49: https://goias.gov.br/saude/cemac-juarez-barbosa/ | K49: Pedido, renovação e acompanhamento são online pelo go.gov.br. Retirada presencial (Goiânia) ou no município/policlínica (interior). | L49: Protótipo do app (ver aba Fontes) | M49: Ativo | P49: =IF($A49="","",IF($M49="Inativo","Não",IF($N49="","Sim",IF(TODAY()-$N49>180,"Sim","Não"))))
A50: cta | B50: CTA/SAE Centro de Saúde Cidade Jardim (HIV, IST e hepatites) | C50: Saúde | D50: Goiânia | F50: Praça Abel Coimbra, s/n, Cidade Jardim, Goiânia, CEP 74425-250 | G50: (62) 3524-1570 / (62) 3524-1577 | I50: Seg a sex, 7h às 19h | K50: Testagem rápida, aconselhamento, infectologista, entrega contínua de antirretrovirais e PrEP. Recebeu os serviços do antigo CRDT. | L50: Protótipo do app (ver aba Fontes) | M50: Ativo | P50: =IF($A50="","",IF($M50="Inativo","Não",IF($N50="","Sim",IF(TODAY()-$N50>180,"Sim","Não"))))
A51: hdt | B51: HDT, Hospital Estadual de Doenças Tropicais Dr. Anuar Auad | C51: Saúde | D51: Estado | F51: Av. Contorno, s/n, Jardim Bela Vista, Goiânia, CEP 74853-120 | G51: Recepção (62) 3201-3658 / Ouvidoria (62) 3201-3799 | K51: Referência estadual em infectologia e HIV/aids. Oferece PEP e PrEP. Programa Prevenir para a Vida (gestantes). | L51: Protótipo do app (ver aba Fontes) | M51: Ativo | P51: =IF($A51="","",IF($M51="Inativo","Não",IF($N51="","Sim",IF(TODAY()-$N51>180,"Sim","Não"))))
A52: pep-noroeste | B52: UPA Noroeste (PEP 24h) | C52: Saúde | D52: Goiânia | F52: Rua JC-22, Jardim Curitiba | G52: (62) 3524-3461 | K52: Profilaxia pós-exposição ao HIV, até 72h. Lista de 2024: confirme por telefone. | L52: Protótipo do app (ver aba Fontes) | M52: A conferir | P52: =IF($A52="","",IF($M52="Inativo","Não",IF($N52="","Sim",IF(TODAY()-$N52>180,"Sim","Não"))))
A53: pep-itaipu | B53: UPA Itaipu (PEP 24h) | C53: Saúde | D53: Goiânia | F53: Av. do Povo, 13 | G53: (62) 3524-2560 | K53: PEP até 72h. Lista de 2024: confirme por telefone. | L53: Protótipo do app (ver aba Fontes) | M53: A conferir | P53: =IF($A53="","",IF($M53="Inativo","Não",IF($N53="","Sim",IF(TODAY()-$N53>180,"Sim","Não"))))
A54: pep-novomundo | B54: UPA Jardim Novo Mundo (PEP 24h) | C54: Saúde | D54: Goiânia | F54: Av. New York, Qd. 137, s/n, Jd. Novo Mundo | G54: (62) 3524-5073 | K54: PEP até 72h. Lista de 2024: confirme por telefone. | L54: Protótipo do app (ver aba Fontes) | M54: A conferir | P54: =IF($A54="","",IF($M54="Inativo","Não",IF($N54="","Sim",IF(TODAY()-$N54>180,"Sim","Não"))))
A55: pep-chacara | B55: UPA Chácara do Governador (PEP 24h) | C55: Saúde | D55: Goiânia | F55: Rua DF-02, Lt. 14, esq. Rua DF-18 | G55: (62) 3246-2705 | K55: PEP até 72h. Lista de 2024: confirme por telefone. | L55: Protótipo do app (ver aba Fontes) | M55: A conferir | P55: =IF($A55="","",IF($M55="Inativo","Não",IF($N55="","Sim",IF(TODAY()-$N55>180,"Sim","Não"))))
A56: pep-goia | B56: CAIS Bairro Goiá (PEP 24h) | C56: Saúde | D56: Goiânia | F56: Av. Santa Maria, s/n, Bairro Goiá | G56: (62) 3519-1781 | K56: PEP até 72h. Lista de 2024: confirme por telefone. | L56: Protótipo do app (ver aba Fontes) | M56: A conferir | P56: =IF($A56="","",IF($M56="Inativo","Não",IF($N56="","Sim",IF(TODAY()-$N56>180,"Sim","Não"))))
A57: pep-campinas | B57: CAIS Campinas (PEP 24h) | C57: Saúde | D57: Goiânia | F57: Rua P-16 c/ P-30, Campinas | G57: (62) 3524-1930 | K57: PEP até 72h. Lista de 2024: confirme por telefone. | L57: Protótipo do app (ver aba Fontes) | M57: A conferir | P57: =IF($A57="","",IF($M57="Inativo","Não",IF($N57="","Sim",IF(TODAY()-$N57>180,"Sim","Não"))))
A58: pep-vilanova | B58: CAIS Vila Nova (PEP 24h) | C58: Saúde | D58: Goiânia | F58: Rua B, 56, Vila Viana | G58: (62) 3524-1826 | K58: PEP até 72h. Lista de 2024: confirme por telefone. | L58: Protótipo do app (ver aba Fontes) | M58: A conferir | P58: =IF($A58="","",IF($M58="Inativo","Não",IF($N58="","Sim",IF(TODAY()-$N58>180,"Sim","Não"))))
A59: fp | B59: Farmácia Popular (farmácias credenciadas) | C59: Saúde | D59: Nacional | J59: https://www.gov.br/saude/pt-br/composicao/sectics/farmacia-popular | K59: Procure o selo "Aqui Tem Farmácia Popular". O endereço das credenciadas está no painel do gov.br. Os mesmos medicamentos também saem de graça nas UBS. | L59: Protótipo do app (ver aba Fontes) | M59: Ativo | P59: =IF($A59="","",IF($M59="Inativo","Não",IF($N59="","Sim",IF(TODAY()-$N59>180,"Sim","Não"))))
A60: 136 | B60: Disque Saúde 136, Ouvidoria do SUS | C60: Nacional | D60: Nacional | G60: 136 | K60: Informações sobre SUS, Farmácia Popular e reclamações. | L60: Protótipo do app (ver aba Fontes) | M60: Ativo | P60: =IF($A60="","",IF($M60="Inativo","Não",IF($N60="","Sim",IF(TODAY()-$N60>180,"Sim","Não"))))
A61: reggyn | B61: Regulação da Saúde de Goiânia | C61: Saúde | D61: Goiânia | G61: (62) 3524-1580 / (62) 3524-1616 | K61: Consultas especializadas e exames encaminhados pela UBS. | L61: Protótipo do app (ver aba Fontes) | M61: Ativo | P61: =IF($A61="","",IF($M61="Inativo","Não",IF($N61="","Sim",IF(TODAY()-$N61>180,"Sim","Não"))))
A62: dpe | B62: Defensoria Pública de Goiás, sede | C62: Justiça e direitos | D62: Goiânia | F62: Alameda Cel. Joaquim de Bastos, nº 282, Qd. 217, Lt. 14, Setor Marista, Goiânia | G62: Central (62) 3602-1224 | I62: Seg a sex, 8h às 18h | J62: https://www2.defensoria.go.def.br/unidades-de-atendimento | K62: Família, moradia, documentos, benefício negado, medida protetiva. Lista de documentos no site. | L62: Protótipo do app (ver aba Fontes) | M62: Ativo | P62: =IF($A62="","",IF($M62="Inativo","Não",IF($N62="","Sim",IF(TODAY()-$N62>180,"Sim","Não"))))
A63: mpgo | B63: MPGO, Ministério Público de Goiás, sede e atendimento ao cidadão | C63: Ministério Público | D63: Estado | F63: Rua 23 esq. c/ Av. Fued José Sebba, Qd. A-06, Lts. 15/24, Jardim Goiás, Goiânia, CEP 74805-100 | G63: (62) 3243-8000 | J63: https://www.mpgo.mp.br/portal/pagina/atendimento-ao-cidadao | K63: Representação contra omissão do poder público, defesa coletiva de criança, idoso, PcD, saúde, educação, consumidor e vítimas de violência. Pode ser feita online ou na promotoria da comarca onde a pessoa mora. | L63: Protótipo do app (ver aba Fontes) | M63: Ativo | P63: =IF($A63="","",IF($M63="Inativo","Não",IF($N63="","Sim",IF(TODAY()-$N63>180,"Sim","Não"))))
A64: mpgo-dh | B64: MPGO, Centro de Apoio de Políticas Públicas e Direitos Humanos (CAO DH) | C64: Ministério Público | D64: Estado | F64: Edifício-sede do MPGO, Sala T-10, térreo, Ala A, Goiânia | G64: (62) 3243-8203 / (62) 3243-8711 / (62) 3243-8347 / Plantão (62) 92002-7158 | H64: caodh@mpgo.mp.br | K64: Apoia as promotorias em direitos humanos, população de rua, idoso, PcD e vítimas e testemunhas ameaçadas. | L64: Protótipo do app (ver aba Fontes) | M64: Ativo | P64: =IF($A64="","",IF($M64="Inativo","Não",IF($N64="","Sim",IF(TODAY()-$N64>180,"Sim","Não"))))
A65: mpgo-gen | B65: MPGO, Núcleo Estadual de Gênero | C65: Ministério Público | D65: Estado | G65: (62) 3243-8665 | K65: Atua na violência contra a mulher e acompanha medidas protetivas. Fonte: cartilha OAB-GO, março de 2026. | L65: cartilha OAB-GO, março de 2026 | M65: Ativo | P65: =IF($A65="","",IF($M65="Inativo","Não",IF($N65="","Sim",IF(TODAY()-$N65>180,"Sim","Não"))))
A66: mpf | B66: MPF, Procuradoria da República em Goiás | C66: Ministério Público | D66: Estado | F66: Av. Olinda, nº 500, Qd. G, Lt. 2, Ed. Rosângela Pofahl Batista, Park Lozandes, Goiânia, CEP 74884-120 | G66: (62) 3243-5400 / WhatsApp (62) 99513-3507 (seg a sex, 10h às 17h) | J66: https://www.mpf.mp.br/servicos | K66: Assuntos federais: INSS e BPC, programas federais, universidades e hospitais federais, indígenas e quilombolas, verba federal do SUS. | L66: Protótipo do app (ver aba Fontes) | M66: Ativo | P66: =IF($A66="","",IF($M66="Inativo","Não",IF($N66="","Sim",IF(TODAY()-$N66>180,"Sim","Não"))))
A67: mpt | B67: MPT, Ministério Público do Trabalho (Goiás) | C67: Ministério Público | D67: Nacional | J67: https://mpt.mp.br | K67: Trabalho infantil, trabalho escravo, assédio, discriminação no emprego (inclusive por HIV ou deficiência), falta de acessibilidade. Denúncia online pelo site, com sigilo. | L67: Protótipo do app (ver aba Fontes) | M67: Ativo | P67: =IF($A67="","",IF($M67="Inativo","Não",IF($N67="","Sim",IF(TODAY()-$N67>180,"Sim","Não"))))
A68: provita | B68: Provita/GO e SEPDE, proteção a vítimas e testemunhas ameaçadas | C68: Ministério Público | D68: Estado | F68: Av. Anhanguera, 7364, Aeroviário, Goiânia, CEP 74435-300 | G68: (62) 3201-1069 / (62) 3201-1068 | K68: Inclusão depende de pedido da autoridade (MP, polícia, juiz). Acione pelo promotor do caso. | L68: Protótipo do app (ver aba Fontes) | M68: Ativo | P68: =IF($A68="","",IF($M68="Inativo","Não",IF($N68="","Sim",IF(TODAY()-$N68>180,"Sim","Não"))))
A69: dpeap | B69: Defensoria Pública, unidade Aparecida de Goiânia | C69: Justiça e direitos | D69: Aparecida de Goiânia | G69: (62) 3157-1001 | L69: Protótipo do app (ver aba Fontes) | M69: Ativo | P69: =IF($A69="","",IF($M69="Inativo","Não",IF($N69="","Sim",IF(TODAY()-$N69>180,"Sim","Não"))))
A70: puc-npj | B70: NPJ PUC Goiás, Núcleo de Prática Jurídica | C70: Rede comunitária e gratuita | D70: Goiânia | F70: Câmpus V, Jardim Goiás, Goiânia | G70: (62) 3946-3008 / (62) 3946-3009 | H70: npj@pucgoias.edu.br | K70: Escritório-modelo: atendimento jurídico gratuito para quem não pode pagar. Alternativa à Defensoria. Fonte: PUC Goiás, 2023. | L70: PUC Goiás, 2023 | M70: Ativo | P70: =IF($A70="","",IF($M70="Inativo","Não",IF($N70="","Sim",IF(TODAY()-$N70>180,"Sim","Não"))))
A71: puc-cepsi | B71: CEPSI PUC Goiás, clínica-escola de psicologia | C71: Rede comunitária e gratuita | D71: Goiânia | F71: Rua 232, Área 5, Setor Leste Universitário, Goiânia | G71: (62) 3946-1198 | J71: https://www.pucgoias.edu.br | K71: Atendimento psicológico gratuito para todas as idades. Inscrições no início de cada semestre pelo site. | L71: Protótipo do app (ver aba Fontes) | M71: Ativo | P71: =IF($A71="","",IF($M71="Inativo","Não",IF($N71="","Sim",IF(TODAY()-$N71>180,"Sim","Não"))))
A72: ufg-psi | B72: Centro de Psicologia da Faculdade de Educação, UFG | C72: Rede comunitária e gratuita | D72: Goiânia | F72: Rua 235, nº 575, Setor Leste Universitário, Goiânia, CEP 74605-050 | K72: Psicoterapia gratuita, prioridade para baixa renda. Adultos e crianças de 5 a 11 anos. Inscrição presencial em períodos divulgados pela UFG (última em abril de 2025). | L72: Protótipo do app (ver aba Fontes) | M72: Ativo | P72: =IF($A72="","",IF($M72="Inativo","Não",IF($N72="","Sim",IF(TODAY()-$N72>180,"Sim","Não"))))
A73: puc-vida | B73: Clínica Escola Vida, PUC Goiás | C73: Rede comunitária e gratuita | D73: Goiânia | F73: Rua Colônia, Jardim Novo Mundo, Goiânia | G73: (62) 3946-1808 | K73: Clínica-escola de saúde que atende pessoas encaminhadas pelo SUS. Pedir o encaminhamento na UBS. | L73: Protótipo do app (ver aba Fontes) | M73: Ativo | P73: =IF($A73="","",IF($M73="Inativo","Não",IF($N73="","Sim",IF(TODAY()-$N73>180,"Sim","Não"))))
A74: puc-cresa | B74: CRESA PUC Goiás, saúde auditiva | C74: Rede comunitária e gratuita | D74: Goiânia | F74: Área 5, Rua 232, Setor Leste Universitário, Goiânia | G74: (62) 3946-1419 | K74: Saúde auditiva em parceria com o SUS (avaliação e aparelhos). Acesso por encaminhamento da UBS. | L74: Protótipo do app (ver aba Fontes) | M74: Ativo | P74: =IF($A74="","",IF($M74="Inativo","Não",IF($N74="","Sim",IF(TODAY()-$N74>180,"Sim","Não"))))
A75: puc-cecom | B75: Cecom e Escola de Circo Dom Fernando, PUC Goiás | C75: Rede comunitária e gratuita | D75: Goiânia | F75: Rua 15, Setor Santos Dumont, Goiânia | G75: (62) 3299-7753 | K75: Extensão comunitária nas regiões Mendanha e Noroeste: circo, formação de jovens de 14 a 29 anos. | L75: Protótipo do app (ver aba Fontes) | M75: Ativo | P75: =IF($A75="","",IF($M75="Inativo","Não",IF($N75="","Sim",IF(TODAY()-$N75>180,"Sim","Não"))))
A76: ceapsol | B76: Ceap-SOL, Casa de Apoio Condomínio Solidariedade | C76: Rede comunitária e gratuita | D76: Goiânia | F76: Av. Veneza, Qd. 62, Lt. 1/10, s/n, Jardim Europa, Goiânia, CEP 74325-100 | G76: Recepção (62) 3201-9288 / Hospedagem/WhatsApp (62) 3201-9283 | I76: Serviço Social seg a sex, 7h às 18h | K76: Unidade estadual. Hospedagem gratuita, alimentação e transporte para consultas de pessoas vivendo com HIV, principalmente do interior. Pedir com antecedência. | L76: Protótipo do app (ver aba Fontes) | M76: Ativo | P76: =IF($A76="","",IF($M76="Inativo","Não",IF($N76="","Sim",IF(TODAY()-$N76>180,"Sim","Não"))))
A77: cevam | B77: CEVAM, Centro de Valorização da Mulher Consuelo Nasser | C77: Rede comunitária e gratuita | D77: Goiânia | G77: (62) 99144-5948 | K77: Entidade filantrópica que acolhe mulheres em situação de violência com seus filhos e distribui cestas a famílias. Endereço não divulgado por segurança. O acolhimento é articulado pela rede (DEAEM, Cora Coralina, CREAS). | L77: Protótipo do app (ver aba Fontes) | M77: Ativo | P77: =IF($A77="","",IF($M77="Inativo","Não",IF($N77="","Sim",IF(TODAY()-$N77>180,"Sim","Não"))))
A78: deaem | B78: DEAEM, Delegacia Estadual de Atendimento Especializado à Mulher | C78: Mulher | D78: Goiânia | F78: Rua 24, nº 203, Qd. 49, Lt. 27, Centro, Goiânia, CEP 74030-060 | G78: (62) 3201-2013 / Plantão (62) 3201-2802 | H78: deaem@policiacivil.go.gov.br | I78: Plantão 24h | K78: Registro de ocorrência e pedido de medida protetiva. | L78: Protótipo do app (ver aba Fontes) | M78: Ativo | P78: =IF($A78="","",IF($M78="Inativo","Não",IF($N78="","Sim",IF(TODAY()-$N78>180,"Sim","Não"))))
A79: plantao | B79: Polícia Civil, Plantão 24h (Cidade Jardim) | C79: Mulher | D79: Goiânia | F79: Av. Atílio Corrêa Lima, s/n, Cidade Jardim, Goiânia, CEP 74425-030 | G79: (62) 3201-2013 / Plantão (62) 3201-2801 | H79: deaem@policiacivil.go.gov.br | I79: 24h | L79: Protótipo do app (ver aba Fontes) | M79: Ativo | P79: =IF($A79="","",IF($M79="Inativo","Não",IF($N79="","Sim",IF(TODAY()-$N79>180,"Sim","Não"))))
A80: cora | B80: Centro de Referência da Mulher Cora Coralina | C80: Mulher | D80: Goiânia | F80: Rua 8 c/ Rua 9, nº 558, Ed. Small Tower, Setor Oeste, Goiânia | G80: (62) 3524-2422 / (62) 3524-2934 | H80: secmulher@goiania.go.gov.br | I80: Seg a sex, 8h às 17h | K80: Atendimento social, psicológico e jurídico. Faz o encaminhamento para a Casa Abrigo Sempre Viva (endereço sigiloso). | L80: Protótipo do app (ver aba Fontes) | M80: Ativo | P80: =IF($A80="","",IF($M80="Inativo","Não",IF($N80="","Sim",IF(TODAY()-$N80>180,"Sim","Não"))))
A81: bmp | B81: Batalhão Maria da Penha (PM) | C81: Mulher | D81: Goiânia | F81: Av. Perimetral esq. c/ Av. T-6, Setor Coimbra, Goiânia, CEP 74530-020 | G81: (62) 99930-9778 / Emergência 190 | I81: Seg a sex, 8h às 12h e 14h às 18h | K81: Fiscaliza medidas protetivas. | L81: Protótipo do app (ver aba Fontes) | M81: Ativo | P81: =IF($A81="","",IF($M81="Inativo","Não",IF($N81="","Sim",IF(TODAY()-$N81>180,"Sim","Não"))))
A82: gcm | B82: Patrulha Mulher Mais Segura (GCM Goiânia) | C82: Mulher | D82: Goiânia | G82: 153 | K82: Visitas a mulheres com medida protetiva e botão de pânico no app Prefeitura 24h. | L82: Protótipo do app (ver aba Fontes) | M82: Ativo | P82: =IF($A82="","",IF($M82="Inativo","Não",IF($N82="","Sim",IF(TODAY()-$N82>180,"Sim","Não"))))
A83: pop | B83: Centro POP Goiânia | C83: CREAS e Centro POP | D83: Goiânia | F83: Rua Francisca Costa Cunha Tita, Setor Aeroporto, Goiânia | I83: Todos os dias, 7h às 17h | K83: Alimentação, higiene, documentos e encaminhamentos para pessoas em situação de rua. Telefone direto não localizado: use a gestão da assistência social abaixo. | L83: Protótipo do app (ver aba Fontes) | M83: Ativo | P83: =IF($A83="","",IF($M83="Inativo","Não",IF($N83="","Sim",IF(TODAY()-$N83>180,"Sim","Não"))))
A84: gestaogyn | B84: Assistência Social de Goiânia (Semasdh), gestão da proteção especial | C84: CREAS e Centro POP | D84: Goiânia | F84: Rua 25-A esq. c/ Av. República do Líbano, Qd. 63, s/n, Setor Aeroporto, Goiânia | G84: (62) 3524-2603 / (62) 3524-2714 | H84: sedhs@goiania.go.gov.br | I84: Seg a sex, 8h às 18h | L84: Protótipo do app (ver aba Fontes) | M84: Ativo | P84: =IF($A84="","",IF($M84="Inativo","Não",IF($N84="","Sim",IF(TODAY()-$N84>180,"Sim","Não"))))
A85: creas-cs | B85: CREAS Centro-Sul | C85: CREAS e Centro POP | D85: Goiânia | E85: centro-sul | F85: Rua 104, nº 614, Setor Sul | G85: (62) 3524-4607 / (62) 99208-4933 | L85: Protótipo do app (ver aba Fontes) | M85: Ativo | P85: =IF($A85="","",IF($M85="Inativo","Não",IF($N85="","Sim",IF(TODAY()-$N85>180,"Sim","Não"))))
A86: creas-l | B86: CREAS Leste | C86: CREAS e Centro POP | D86: Goiânia | E86: leste | F86: Rua Indiana, Qd. 21, Jardim Novo Mundo | G86: (62) 3524-1770 / (62) 99210-4518 | L86: Protótipo do app (ver aba Fontes) | M86: Ativo | P86: =IF($A86="","",IF($M86="Inativo","Não",IF($N86="","Sim",IF(TODAY()-$N86>180,"Sim","Não"))))
A87: creas-no | B87: CREAS Noroeste | C87: CREAS e Centro POP | D87: Goiânia | E87: noroeste | F87: Rua da República c/ Cláudio Manoel da Costa, Qd. 20, Lt. 32, Setor Capuava | G87: (62) 3524-3431 / (62) 99208-2462 | L87: Protótipo do app (ver aba Fontes) | M87: Ativo | P87: =IF($A87="","",IF($M87="Inativo","Não",IF($N87="","Sim",IF(TODAY()-$N87>180,"Sim","Não"))))
A88: creas-n | B88: CREAS Norte | C88: CREAS e Centro POP | D88: Goiânia | E88: norte | F88: Alameda Capim Puba, nº 60, Qd. 01, Lt. 04, Setor Centro-Oeste | G88: (62) 3524-2147 / (62) 99210-7904 | L88: Protótipo do app (ver aba Fontes) | M88: Ativo | P88: =IF($A88="","",IF($M88="Inativo","Não",IF($N88="","Sim",IF(TODAY()-$N88>180,"Sim","Não"))))
A89: creas-o | B89: CREAS Oeste | C89: CREAS e Centro POP | D89: Goiânia | E89: oeste | F89: Av. Sonemberg c/ Antônio Xavier, nº 01, Praça Conj. Romildo Francisco Amaral, Setor Cidade Jardim | G89: (62) 3524-6914 / (62) 99206-0636 | L89: Protótipo do app (ver aba Fontes) | M89: Ativo | P89: =IF($A89="","",IF($M89="Inativo","Não",IF($N89="","Sim",IF(TODAY()-$N89>180,"Sim","Não"))))
A90: ct-cs | B90: Conselho Tutelar Centro-Sul | C90: Conselho Tutelar | D90: Goiânia | E90: centro-sul | G90: (62) 3524-1760 | K90: Regiões Central e Sul. | L90: Protótipo do app (ver aba Fontes) | M90: Ativo | P90: =IF($A90="","",IF($M90="Inativo","Não",IF($N90="","Sim",IF(TODAY()-$N90>180,"Sim","Não"))))
A91: ct-l | B91: Conselho Tutelar Leste | C91: Conselho Tutelar | D91: Goiânia | E91: leste | G91: (62) 3524-1743 | K91: Regiões Leste e Sudeste. | L91: Protótipo do app (ver aba Fontes) | M91: Ativo | P91: =IF($A91="","",IF($M91="Inativo","Não",IF($N91="","Sim",IF(TODAY()-$N91>180,"Sim","Não"))))
A92: ct-n | B92: Conselho Tutelar Norte | C92: Conselho Tutelar | D92: Goiânia | E92: norte | G92: (62) 3524-2404 | K92: Regiões Vale do Meia Ponte e Norte. | L92: Protótipo do app (ver aba Fontes) | M92: Ativo | P92: =IF($A92="","",IF($M92="Inativo","Não",IF($N92="","Sim",IF(TODAY()-$N92>180,"Sim","Não"))))
A93: ct-o | B93: Conselho Tutelar Oeste | C93: Conselho Tutelar | D93: Goiânia | E93: oeste | G93: (62) 3524-1765 | K93: Regiões Macambira/Cascavel e Sudoeste. | L93: Protótipo do app (ver aba Fontes) | M93: Ativo | P93: =IF($A93="","",IF($M93="Inativo","Não",IF($N93="","Sim",IF(TODAY()-$N93>180,"Sim","Não"))))
A94: ct-no | B94: Conselho Tutelar Noroeste | C94: Conselho Tutelar | D94: Goiânia | E94: noroeste | G94: (62) 3524-3446 | K94: Regiões Mendanha e Noroeste. | L94: Protótipo do app (ver aba Fontes) | M94: Ativo | P94: =IF($A94="","",IF($M94="Inativo","Não",IF($N94="","Sim",IF(TODAY()-$N94>180,"Sim","Não"))))
A95: ct-c | B95: Conselho Tutelar Campinas | C95: Conselho Tutelar | D95: Goiânia | E95: campinas | G95: (62) 3524-2481 | K95: Regiões Campinas e Oeste. | L95: Protótipo do app (ver aba Fontes) | M95: Ativo | P95: =IF($A95="","",IF($M95="Inativo","Não",IF($N95="","Sim",IF(TODAY()-$N95>180,"Sim","Não"))))
A96: semas-ap | B96: Secretaria de Assistência Social de Aparecida | C96: CRAS | D96: Aparecida de Goiânia | G96: (62) 3545-5970 | K96: Informa o CRAS de referência do bairro (o município tem 8 unidades). | L96: Protótipo do app (ver aba Fontes) | M96: Ativo | P96: =IF($A96="","",IF($M96="Inativo","Não",IF($N96="","Sim",IF(TODAY()-$N96>180,"Sim","Não"))))
A97: creas-ap | B97: CREAS II Aparecida | C97: CREAS e Centro POP | D97: Aparecida de Goiânia | F97: Rua 07, Jardim Tiradentes, Aparecida de Goiânia | G97: (62) 3545-9980 | L97: Protótipo do app (ver aba Fontes) | M97: Ativo | P97: =IF($A97="","",IF($M97="Inativo","Não",IF($N97="","Sim",IF(TODAY()-$N97>180,"Sim","Não"))))
A98: ct-ap-c | B98: Conselho Tutelar Regional Centro (Aparecida) | C98: Conselho Tutelar | D98: Aparecida de Goiânia | F98: Av. B, Qd. F, Lt. 01 | G98: (62) 3545-5880 / (62) 99282-9025 | H98: ctutelarapgyn132@gmail.com | L98: Protótipo do app (ver aba Fontes) | M98: Ativo | P98: =IF($A98="","",IF($M98="Inativo","Não",IF($N98="","Sim",IF(TODAY()-$N98>180,"Sim","Não"))))
A99: ct-ap-g | B99: Conselho Tutelar Regional Garavelo (Aparecida) | C99: Conselho Tutelar | D99: Aparecida de Goiânia | F99: Av. Tropical, Qd. 25, Lt. 04 | G99: (62) 3545-4897 / (62) 98459-9726 | L99: Protótipo do app (ver aba Fontes) | M99: Ativo | P99: =IF($A99="","",IF($M99="Inativo","Não",IF($N99="","Sim",IF(TODAY()-$N99>180,"Sim","Não"))))
A100: dpca-ap | B100: DPCA, Delegacia de Proteção à Criança e ao Adolescente | C100: Justiça e direitos | D100: Aparecida de Goiânia | F100: Av. Furnas, Qd. 03, Lt. 8/9, Residencial Maria Luíza | G100: (62) 3201-2295 | L100: Protótipo do app (ver aba Fontes) | M100: Ativo | P100: =IF($A100="","",IF($M100="Inativo","Não",IF($N100="","Sim",IF(TODAY()-$N100>180,"Sim","Não"))))
...

Sheet Políticas
A1: ID (não altere) | B1: Nome | C1: Nome curto | D1: Esfera | E1: Valor ou benefício | F1: Passo a passo (um passo por linha) | G1: Documentos (um por linha) | H1: Onde ir (tipo de lugar) | I1: Outros contatos (IDs da aba Serviços) | J1: Fonte | K1: Conferido em | L1: Mudança de critério pedida
A2: cad | B2: Cadastro Único (CadÚnico) | C2: CadÚnico | D2: Nacional | E2: Porta de entrada | F2: Procurar o CRAS de referência com documento com foto e CPF de todos da casa e comprovante de endereço. Responder à entrevista com o entrevistador do CadÚnico. Guardar o número do NIS e atualizar sempre que mudar endereço, renda ou composição da família (no máximo a cada 2 anos). | G2: CPF de todos da casa (ou título de eleitor) Documento com foto do responsável familiar Comprovante de endereço (ajuda, não é obrigatório) Carteira de trabalho, se tiver | H2: cras | I2: 121 | J2: Ver aba Fontes e docs/levantamento-2026-10-08.md
A3: pbf | B3: Bolsa Família | D3: Nacional | E3: mín. R$ 600/família + adicionais | F3: Fazer ou atualizar o CadÚnico no CRAS. A seleção é automática pelo governo federal, conforme orçamento e ordem de renda. Acompanhar pelo app Bolsa Família, Caixa Tem ou pelo 121. Manter as condicionalidades: vacinação, pré-natal e frequência escolar. | G3: Os mesmos do CadÚnico | H3: cras | I3: 121 | J3: Ver aba Fontes e docs/levantamento-2026-10-08.md
A4: bpc | B4: BPC, Benefício de Prestação Continuada | C4: BPC | D4: Nacional | E4: 1 salário mínimo/mês | F4: Ter o CadÚnico atualizado (obrigatório). Pedir pelo Meu INSS ou pelo 135. Pessoa com deficiência: fazer avaliação social e perícia médica no INSS. Se negado, procurar a Defensoria Pública para recorrer. | G4: Documento com foto e CPF do requerente e da família Laudos e exames (pessoa com deficiência) Número do NIS | H4: cras | I4: 135, dpe, mpf, puc-npj | J4: Ver aba Fontes e docs/levantamento-2026-10-08.md
A5: tse | B5: Tarifa Social de Energia Elétrica | C5: Tarifa Social | D5: Nacional | E5: Luz grátis até 80 kWh/mês | F5: Ter o CadÚnico atualizado, com o endereço da conta de luz. Desde julho de 2025, o consumo até 80 kWh por mês é gratuito; o que passar disso é cobrado normalmente. Impostos e iluminação pública continuam na conta. A concessão costuma ser automática. Se não aparecer, pedir à distribuidora (Equatorial Goiás) informando o NIS. A conta precisa estar no nome de alguém da família. | G5: NIS Conta de luz no nome de alguém da família | H5: cras | J5: Ver aba Fontes e docs/levantamento-2026-10-08.md
A6: gas | B6: Gás do Povo (botijão gratuito) | C6: Gás do Povo | D6: Nacional | E6: Botijão de 13 kg sem custo | F6: Não há inscrição: o MDS seleciona pelo CadÚnico (atualizado nos últimos 24 meses), com prioridade para quem recebe Bolsa Família. Consultar pelo app Meu Social ou pelo 121. Selecionado: levar o botijão vazio a uma revenda credenciada e trocar pelo cheio, sem pagar. O governo não cobra taxa: desconfie de quem pedir dinheiro. | G6: CPF do responsável familiar | H6: cras | I6: 121 | J6: Ver aba Fontes e docs/levantamento-2026-10-08.md
A7: mcmv | B7: Minha Casa, Minha Vida (Faixa 1) | C7: Minha Casa, Minha Vida | D7: Nacional | E7: Moradia subsidiada | F7: Faixa 1 (baixa renda): inscrição pela prefeitura (Goiânia: site e app Prefeitura 24h) ou pela Agehab, quando abrem cadastro. Faixas 2 e 3: direto na Caixa. Ter o CadÚnico atualizado. Acompanhar a abertura de cadastros: a seleção segue os critérios do edital (mulher chefe de família, PcD, idoso, área de risco, violência doméstica). Enquanto espera: Aluguel Social (Agehab), se tiver direito. | G7: Documento com foto e CPF de todos Comprovante de renda CadÚnico | I7: agehab | J7: Ver aba Fontes e docs/levantamento-2026-10-08.md
A8: pdm | B8: Pé-de-Meia | D8: Nacional | E8: Poupança para estudante | F8: Manter matrícula e frequência no ensino médio público. Família com CadÚnico atualizado. Consultar pelo app Jornada do Estudante ou pela escola. | G8: CPF do estudante | H8: cras | J8: Ver aba Fontes e docs/levantamento-2026-10-08.md
A9: cpi | B9: Carteira da Pessoa Idosa | C9: Carteira da Pessoa Idosa | D9: Nacional | E9: Passagem interestadual gratuita ou com desconto | F9: Fazer ou atualizar o CadÚnico. Emitir a carteira no CRAS ou pelo site da Carteira da Pessoa Idosa (MDS). Reservar a vaga na empresa de ônibus com antecedência. | G9: Documento com foto NIS | H9: cras | J9: Ver aba Fontes e docs/levantamento-2026-10-08.md
A10: plfed | B10: Passe Livre interestadual (pessoa com deficiência) | C10: Passe Livre interestadual | D10: Nacional | E10: Viagem interestadual gratuita | F10: Pedir pelo site do Ministério dos Transportes (Passe Livre). Anexar laudo médico e comprovante de renda ou CadÚnico. | G10: Laudo Documento com foto CadÚnico ou comprovante de renda | H10: cras | J10: Ver aba Fontes e docs/levantamento-2026-10-08.md
A11: maes | B11: Mães de Goiás | D11: Estadual | E11: R$ 300/mês | F11: Não tem inscrição. O Estado seleciona 1 ou 2 vezes por ano pela base do CadÚnico. Manter o CadÚnico atualizado no CRAS, com vacinação e frequência escolar das crianças em dia. A prefeitura avisa por SMS ou WhatsApp o dia e o local de entrega do cartão. Consultar situação em suas.social.go.gov.br/consulta-maesdegoias. 2ª via só pelo (62) 3270-9610. | G11: Documento com foto e CPF da beneficiária (para retirar o cartão) | H11: cras | I11: mxc | J11: Ver aba Fontes e docs/levantamento-2026-10-08.md
A12: inclusivo | B12: Goiás + Inclusivo | D12: Estadual | E12: R$ 500/mês | F12: Seleção automática pelo CadÚnico, sem inscrição. Conferir no CRAS se a deficiência está registrada no cadastro. O município avisa a data de entrega do cartão. | G12: Documento da pessoa com deficiência e do responsável | H12: cras | I12: mxc | J12: Ver aba Fontes e docs/levantamento-2026-10-08.md
A13: dignidade | B13: Dignidade | D13: Estadual | E13: R$ 300/mês | F13: Sem inscrição: entrada automática pelo CadÚnico. Manter o CadÚnico atualizado no CRAS. Dúvidas e 2ª via: (62) 3270-9610. | G13: Documento com foto | H13: cras | I13: mxc | J13: Ver aba Fontes e docs/levantamento-2026-10-08.md
A14: porelas | B14: Goiás Por Elas | D14: Estadual | E14: R$ 300/mês por até 12 meses | F14: Não há inscrição: a medida protetiva é enviada à Seds pelo TJGO, Defensoria ou Batalhão Maria da Penha. Manter o CadÚnico atualizado. A Seds entra em contato para entrega do cartão. Vale enquanto a medida estiver ativa, até 12 meses. | G14: Cópia da medida protetiva Documento com foto | I14: mulherseds, dpe | J14: Ver aba Fontes e docs/levantamento-2026-10-08.md
A15: aluguel | B15: Pra Ter Onde Morar, Aluguel Social | C15: Aluguel Social | D15: Estadual | E15: R$ 350/mês por 18 meses | F15: Inscrição online em aluguelsocial.agehab.go.gov.br ou no app Aluguel Social (Android). Anexar documentos; análise por ordem de inscrição. Indeferida? Corrigir ou recorrer pelo próprio app. O CRAS pode ajudar a fazer a inscrição. | G15: Comprovantes de água e energia Comprovante de 3 anos no município Contrato ou recibo de aluguel CadÚnico ativo | H15: cras | I15: agehab | J15: Ver aba Fontes e docs/levantamento-2026-10-08.md
A16: ple | B16: Passe Livre Estudantil | D16: Estadual | E16: 48 viagens/mês | F16: Cadastro em juventude.go.gov.br com documentos e foto. Aprovado, agendar a retirada no Vapt Vupt em vaptvupt.go.gov.br/agendamento. Recadastro a cada período letivo. Bloqueio: justificar pelo site da SitPass. | G16: RG CPF Comprovante de endereço Comprovante de matrícula Foto 3x4 | I16: juventude | J16: Ver aba Fontes e docs/levantamento-2026-10-08.md
A17: aprendiz | B17: Aprendiz do Futuro | D17: Estadual | E17: Socioaprendizagem remunerada | F17: Acompanhar a abertura de inscrições em aprendizdofuturo.org.br. Ter CadÚnico (exigido na contratação). Vagas reservadas para PcD. | G17: Documentos do jovem e do responsável Declaração escolar | I17: aprendiz | J17: Ver aba Fontes e docs/levantamento-2026-10-08.md
A18: ciptea | B18: CIPTEA, Carteira de Identificação da Pessoa com Autismo | C18: CIPTEA | D18: Estadual | E18: Documento, válido 5 anos | F18: Preencher o requerimento (site da Seds). Levar à Unidade Maria Xavier Caiado, seg a sex, 8h às 18h. No interior, pedir pelo e-mail pcd@goias.gov.br. Retirar em até 60 dias. | G18: Relatório de neurologista, psiquiatra ou pediatra Certidão de nascimento ou RG com CPF Documentos do responsável Comprovante de endereço em Goiás Foto (ou tirar na hora) | I18: pcd | J18: Ver aba Fontes e docs/levantamento-2026-10-08.md
A19: plpcd | B19: Passe Livre intermunicipal da pessoa com deficiência | C19: Passe Livre PcD | D19: Estadual | E19: Ônibus entre cidades de Goiás | F19: Levar documentos à Unidade Maria Xavier Caiado (Goiânia) ou pedir pelo WhatsApp (62) 98104-3652. Retirar em até 60 dias. Validade de 3 anos. | G19: Laudo de especialista (validade 1 ano) Espelho do CadÚnico Comprovante de residência em Goiás Documentos do acompanhante, se o laudo indicar | I19: pcd | J19: Ver aba Fontes e docs/levantamento-2026-10-08.md
A20: passaporte | B20: Passaporte da Pessoa Idosa | C20: Passaporte da Pessoa Idosa | D20: Estadual | E20: Até 4 viagens/mês entre cidades de Goiás | F20: Goiânia: Unidade Maria Xavier Caiado. Outros municípios: CRAS ou Secretaria de Assistência Social. Comprar o bilhete com até 5h de antecedência (até 500 km). | G20: RG e CPF Comprovante do CadÚnico | H20: cras | I20: passaporte | J20: Ver aba Fontes e docs/levantamento-2026-10-08.md
A21: credito | B21: Crédito Social | D21: Estadual | E21: Até R$ 5 mil, parcela única | F21: Ter CadÚnico de baixa renda. Fazer o curso de capacitação indicado (Seds/Sebrae, Retomada ou Seapa). Receber cartão para compra de equipamentos no comércio local. | G21: CadÚnico Documento com foto | H21: cras | J21: Ver aba Fontes e docs/levantamento-2026-10-08.md
A22: registro | B22: 2ª via gratuita de certidão (Registro Civil) | C22: 2ª via de certidão | D22: Estadual | E22: Gratuito | F22: Ir à Seds (Bloco B, sala 2) ou a um evento do Goiás Social. Sem nenhum dado do registro, a Seds encaminha à Defensoria. | G22: Cópia de qualquer documento, se tiver Comprovante de endereço Telefone | I22: registro, dpe | J22: Ver aba Fontes e docs/levantamento-2026-10-08.md
A23: enem | B23: Enem e isenção da taxa | C23: Enem | D23: Nacional | E23: Porta de entrada para Prouni, Fies e Sisu | F23: Pedir a isenção da taxa na Página do Participante, com a conta gov.br, no prazo do Inep (em abril). Fazer a inscrição no Enem no período do edital, mesmo quem já tem a isenção. Fazer as duas provas. Para Prouni e Fies, a média precisa ser de pelo menos 450 pontos, sem zerar a redação. Quem tinha isenção e faltou precisa justificar a falta para ter isenção no ano seguinte. | G23: CPF Conta gov.br NIS, se estiver no CadÚnico | I23: inep | J23: Ver aba Fontes e docs/levantamento-2026-10-08.md
A24: prouni | B24: Prouni, bolsa em faculdade particular | C24: Prouni | D24: Nacional | E24: Bolsa de 100% ou 50% | F24: Fazer o Enem e conseguir média de pelo menos 450 pontos, sem zerar a redação. Inscrever-se no Prouni com a conta gov.br, nas datas do edital (duas vezes por ano), escolhendo até duas opções de curso. Acompanhar as chamadas e a lista de espera. Pré-selecionado: levar os documentos à faculdade no prazo, para comprovar renda e escola. Manter frequência e aprovação para não perder a bolsa. | G24: Documento com foto e CPF Comprovantes de renda de todos da casa Histórico do ensino médio Comprovante de endereço | I24: mec | J24: Ver aba Fontes e docs/levantamento-2026-10-08.md
A25: fies | B25: Fies e Fies Social, financiamento da faculdade | C25: Fies | D25: Nacional | E25: Financia até 100% no Fies Social | F25: Fazer o Enem (de 2010 em diante) com média de pelo menos 450 pontos, sem zerar a redação. Prova feita como treineiro não vale. Inscrever-se no Fies com a conta gov.br, nas datas do edital (duas vezes por ano). Fies Social: a vaga é identificada pelo CPF na base do CadÚnico. Atualize o cadastro antes da inscrição. Pré-selecionado: validar a inscrição na comissão da faculdade (CPSA) e assinar o contrato no banco. As parcelas do financiamento são pagas depois de formado. | G25: Documento com foto e CPF Comprovantes de renda de todos da casa Conta gov.br | I25: mec | J25: Ver aba Fontes e docs/levantamento-2026-10-08.md
A26: cotas | B26: Universidade pública: Sisu e cotas | C26: Sisu e cotas | D26: Nacional | E26: Gratuito | F26: Fazer o Enem. Inscrever-se no Sisu com a conta gov.br, no início do ano, escolhendo a modalidade de cota. UEG: acompanhar o edital do processo seletivo próprio. Aprovado por cota: levar na matrícula os comprovantes de escola pública e de renda. Já na universidade, procurar a assistência estudantil. | G26: Histórico escolar do ensino médio Comprovantes de renda de todos da casa (cota de renda) Documento com foto e CPF | I26: mec | J26: Ver aba Fontes e docs/levantamento-2026-10-08.md
A27: probem | B27: ProBem, bolsa universitária do Estado (OVG) | C27: ProBem | D27: Estadual | E27: Bolsa integral ou parcial | F27: Ter o CadÚnico feito ou atualizado em Goiás antes da data de corte do edital. Acompanhar a abertura das inscrições no site da OVG (uma vez por semestre). Inscrever-se pelo site da OVG, matriculada ou aprovada em curso presencial de faculdade parceira (confira o edital). Acompanhar o resultado e manter frequência e aprovação. | G27: Documento com foto e CPF Comprovante de matrícula NIS | I27: ovg | J27: Ver aba Fontes e docs/levantamento-2026-10-08.md
A28: pnaes | B28: Assistência estudantil na faculdade | C28: Assistência estudantil | D28: Nacional | E28: Alimentação, moradia, transporte | F28: Procurar a pró-reitoria ou o setor de assistência estudantil da instituição. Acompanhar os editais de auxílio: alimentação, moradia, transporte, creche. Levar os comprovantes de renda da família. Estudante indígena ou quilombola em universidade federal: perguntar pela Bolsa Permanência do MEC. | G28: Comprovantes de renda de todos da casa Comprovante de matrícula Documento com foto e CPF | J28: Ver aba Fontes e docs/levantamento-2026-10-08.md
A29: eja | B29: Terminar os estudos: EJA e Encceja | C29: EJA e Encceja | D29: Nacional | E29: Gratuito | F29: Encceja: inscrição no site do Inep com a conta gov.br, no período do edital. A prova é gratuita. Aprovado em todas as áreas: pedir o certificado à Secretaria de Educação indicada na inscrição. Prefere estudar em sala: matrícula na EJA da escola estadual ou municipal mais próxima. Com o certificado do ensino médio, já pode fazer o Enem e tentar Prouni, Fies e Sisu. | G29: Documento com foto e CPF Histórico escolar, se tiver Comprovante de endereço (para a EJA) | I29: inep | J29: Ver aba Fontes e docs/levantamento-2026-10-08.md
A30: ceaf | B30: Medicamento de alto custo (Componente Especializado, Cemac Juarez Barbosa) | C30: Alto custo | D30: Estadual | E30: Gratuito pelo SUS | F30: Confirmar se o medicamento é fornecido para a doença (CID): consultar a "Relação de medicamentos, doenças e agravos" no site da Cemac. Na consulta, pedir ao médico (SUS ou particular) a LME (Laudo de Solicitação, Avaliação e Autorização de Medicamentos) preenchida, a receita e os exames exigidos pelo protocolo da doença. Baixar no site da Cemac a lista de documentos e exames da doença e conferir se está tudo junto. Criar ou acessar a conta gov.br do paciente. Abrir o pedido online no go.gov.br: serviço "Solicitar abertura de processo ou alteração e/ou inclusão de medicamentos de alto custo". Acompanhar em "Minhas solicitações". A análise leva até 5 dias úteis. Se faltar documento, o pedido volta com a pendência para corrigir. Aprovado: retirar presencialmente. Quem mora em Goiânia retira na Cemac. No interior e na região metropolitana, o local (município ou policlínica) é informado no processo. Renovar online antes de vencer o período autorizado, com nova LME e receita (análise em até 10 dias úteis). Mudou só a dose? Levar a nova receita e o protocolo direto ao guichê de dispensação. Pedido negado ou remédio fora da lista: guardar a resposta por escrito e procurar a Defensoria Pública, que avalia pedido administrativo ou ação judicial. | G30: LME preenchida e assinada pelo médico Receita médica Exames e laudos exigidos pelo protocolo da doença Documento com foto e CPF do paciente Cartão Nacional de Saúde (CNS) Comprovante de endereço Conta gov.br do paciente | I30: cemac, dpe, puc-npj, mpgo, 136 | J30: Ver aba Fontes e docs/levantamento-2026-10-08.md
A31: fpop | B31: Farmácia Popular | D31: Nacional | E31: Gratuito, sem limite de renda | F31: Conferir se o tratamento está entre as indicações do programa (quadro abaixo). Ter receita válida com nome do paciente, nome do medicamento, dose e posologia. Vale receita do SUS ou de médico particular. Ir a uma farmácia com o selo "Aqui Tem Farmácia Popular" (ou consultar o painel de farmácias credenciadas no gov.br). Ligar antes para confirmar se tem o item. Apresentar documento oficial com foto e CPF. O medicamento é entregue de graça. Não pode ir? Um representante legal ou procurador retira com a receita, documentos com foto e CPF dos dois e a procuração ou decisão judicial. Remédio em falta ou recusa indevida: registrar no Disque Saúde 136. Os mesmos medicamentos também saem na UBS do bairro. | G31: Documento oficial com foto e CPF Receita médica dentro da validade Fralda geriátrica: prescrição, laudo ou atestado (PcD: com o CID) Absorvente: autorização do Dignidade Menstrual, válida por 180 dias | I31: fp, 136 | J31: Ver aba Fontes e docs/levantamento-2026-10-08.md
A32: pep | B32: PEP, Profilaxia Pós-Exposição ao HIV | C32: PEP | D32: Rede de proteção | E32: Urgente: até 72h | F32: Ir imediatamente a uma UPA ou CAIS 24h, ou ao HDT. Não esperar o dia seguinte. Fazer o teste rápido de HIV no próprio serviço. Receber os antirretrovirais para 28 dias e tomar todos os dias, sem parar. Retornar para os testes de acompanhamento no CTA Cidade Jardim ou na UBS. Violência sexual: além da PEP, procurar o Hospital Estadual da Mulher (mulheres) e registrar ocorrência, se quiser. | G32: Documento, se tiver. A falta de documento não impede o atendimento. | H32: pep | J32: Ver aba Fontes e docs/levantamento-2026-10-08.md
A33: hivcare | B33: Cuidado contínuo para pessoa vivendo com HIV | C33: Cuidado em HIV | D33: Rede de proteção | E33: SUS gratuito e sigiloso | F33: Fazer o teste rápido na UBS ou no CTA Cidade Jardim. Resultado reagente: o próprio serviço faz a confirmação e o aconselhamento. Vincular-se ao SAE (Serviço de Atendimento Especializado) do CTA Cidade Jardim ou ao HDT para consulta com infectologista. Fazer os exames iniciais (carga viral, CD4 e outros) e começar o tratamento o quanto antes. O tratamento não espera o resultado do CD4. Retirar os antirretrovirais todo mês na unidade dispensadora (o CTA Cidade Jardim faz a entrega contínua). Levar o cartão do SUS. Repetir carga viral e consultas conforme a agenda do SAE. A meta é carga viral indetectável. Gestante vivendo com HIV: pré-natal com acompanhamento do SAE e do programa Prevenir para a Vida do HDT, para evitar a transmissão ao bebê. Apoio emocional: UBS, CAPS ou CVV 188. Discriminação no trabalho, escola ou serviço: Defensoria Pública ou Disque 100. | G33: Cartão do SUS Documento com foto (não é exigido para o teste) | H33: hiv | I33: ceapsol, 100, mpt | J33: Ver aba Fontes e docs/levantamento-2026-10-08.md
A34: prep | B34: PrEP, Profilaxia Pré-Exposição ao HIV | C34: PrEP | D34: Rede de proteção | E34: Comprimido gratuito | F34: Procurar o CTA Cidade Jardim ou o HDT. Fazer teste de HIV e outros exames de triagem. Iniciar o uso diário (ou sob demanda, se indicado pelo profissional). Voltar a cada consulta para testar e retirar novos frascos. | G34: Documento com foto Cartão do SUS | H34: hiv | J34: Ver aba Fontes e docs/levantamento-2026-10-08.md
A35: mp | B35: Ministério Público: quando e como acionar | C35: Ministério Público | D35: Rede de proteção | E35: Gratuito, sem advogado | F35: Primeiro, pedir o serviço por escrito e guardar o comprovante: protocolo, número de atendimento, resposta negativa, receita, laudo ou print. Reclamar na ouvidoria do órgão (SUS 136, ouvidoria da Seds, da prefeitura). Muitas vezes resolve sem processo. Caso individual que precisa de ação na Justiça (um remédio para uma pessoa, guarda, pensão, vaga): Defensoria Pública ou escritório-modelo. Caso que atinge muitas pessoas, ou pessoa vulnerável sem proteção (criança, idoso, PcD, população de rua, falta geral de remédio, fila de cirurgia, escola sem vaga): fazer representação ao Ministério Público certo (quadro abaixo). Registrar a representação no atendimento ao cidadão do site do MP ou presencialmente na promotoria da comarca. Pode pedir sigilo da identidade. Anotar o número da representação e acompanhar. O promotor pode requisitar informações, fazer recomendação, acordo (TAC) ou ação civil pública. Vítima ou testemunha ameaçada: pedir ao promotor do caso a inclusão no Provita. | G35: Relato curto: o que aconteceu, quando, onde, quem foi afetado Comprovantes: protocolos, negativas, laudos, receitas, fotos Contato para retorno (pode pedir sigilo) | I35: mpgo, mpgo-dh, mpf, mpt, dpe | J35: Ver aba Fontes e docs/levantamento-2026-10-08.md
A36: r-mulher | B36: Rede de proteção à mulher | C36: Proteção à mulher | D36: Rede de proteção | E36: Atendimento 24h | F36: Perigo agora: 190 (PM) ou 153 (GCM Goiânia). Registrar ocorrência e pedir medida protetiva na DEAEM (24h). Acompanhamento social, psicológico e jurídico no Centro de Referência Cora Coralina. Risco de morte: Casa Abrigo Sempre Viva, acessada pela rede. Violência sexual: Hospital Estadual da Mulher em até 72h. | G36: Documento com foto, se possível. Não é obrigatório para ser atendida. | H36: mulher | I36: mpgo-gen, cevam, puc-npj | J36: Ver aba Fontes e docs/levantamento-2026-10-08.md
A37: r-crianca | B37: Proteção à criança e ao adolescente | C37: Proteção à criança | D37: Rede de proteção | E37: Conselho Tutelar | F37: Acionar o Conselho Tutelar da região (plantão à noite e no fim de semana). Denúncia anônima: Disque 100. Acompanhamento da família no CREAS. Lesão ou violência sexual: UPA, hospital ou SAMU 192. | G37: Não é preciso documento para denunciar | H37: ct | I37: dpca, mpgo | J37: Ver aba Fontes e docs/levantamento-2026-10-08.md
A38: r-idoso | B38: Proteção a idosos e pessoas com deficiência | C38: Proteção ao idoso e PcD | D38: Rede de proteção | E38: CREAS | F38: Denunciar pelo Disque 100 ou pelo 197 (Polícia Civil). Crime contra a pessoa idosa: Delegacia do Idoso (Goiânia). Acompanhamento no CREAS da região. Casos graves: Ministério Público e Defensoria. | H38: creas | I38: 100, deai, mpgo | J38: Ver aba Fontes e docs/levantamento-2026-10-08.md
A39: r-rua | B39: Atendimento à população em situação de rua | C39: População de rua | D39: Rede de proteção | E39: Centro POP | F39: Ir ao Centro POP (7h às 17h). Fazer o CadÚnico usando o endereço do Centro POP. Pedir vaga em acolhimento pela equipe do Centro POP. Sem documento: 2ª via de certidão e Defensoria. | G39: Nenhum documento é exigido para o primeiro atendimento | H39: pop | I39: mpgo-dh | J39: Ver aba Fontes e docs/levantamento-2026-10-08.md
A40: crise | B40: Manejo da crise suicida | C40: Crise suicida | D40: Rede de proteção | E40: Agir no mesmo dia | F40: Não deixe a pessoa sozinha. Fique com ela, ou com alguém de confiança, até o próximo cuidado começar. Pergunte diretamente: "Você está pensando em se matar?". Perguntar não induz; abre espaço para a pessoa falar. Avalie o risco: há plano (como, quando, onde)? Tem acesso ao meio? Já tentou antes? Está sob efeito de álcool ou drogas agora? Risco alto (plano com meio disponível, tentativa recente, intoxicação, agitação): SAMU 192 ou pronto atendimento agora. A pessoa não vai sozinha. Tomou remédio ou veneno: pronto atendimento mesmo sem sintomas, levando a embalagem. Orientação 24h no CIATox Goiás, 0800 646 4350. Para conversar a qualquer hora: CVV 188, ligação gratuita e sigilosa. Ofereça ligar junto ou salvar o número no celular dela. Reduza o acesso aos meios: com a família, guarde remédios, venenos, armas e cordas fora do alcance. Acione a rede de apoio: um familiar ou pessoa de confiança, de preferência com o conhecimento da pessoa. O risco à vida permite quebrar o sigilo, contando só o necessário. Registre a decisão. Faça com ela um plano de segurança (quadro abaixo). O plano fica com a pessoa, não no app. Garanta o seguimento: CAPS (acesso direto) ou UBS nos próximos dias, com data marcada antes de a pessoa sair. Retome o contato se ela faltar. Tentativa ou autolesão: o serviço de saúde faz a notificação compulsória (ficha de violência autoprovocada, SINAN) em até 24h. A notificação não é denúncia; serve para a rede acompanhar. Cuide de você: discuta o caso com a equipe ou com a supervisão. | G40: Nenhum documento é exigido no atendimento de urgência | H40: saude | I40: 188, ciatox | J40: Ver aba Fontes e docs/levantamento-2026-10-08.md
A41: ad | B41: Álcool e outras drogas: cuidado pelo SUS | C41: Álcool e drogas | D41: Rede de proteção | E41: Gratuito, sem encaminhamento | F41: Primeiro passo: CAPS AD (álcool e drogas) ou UBS. Não precisa de encaminhamento nem de estar sem usar. No CAPS AD a equipe monta um plano de cuidado: consultas, grupos, atendimento à família e, se preciso, remédios. Crise de abstinência grave (convulsão, confusão, delírio, tremor forte) ou intoxicação: SAMU 192 ou UPA. Casos graves: internação breve em leito de hospital geral ou no Credeq (Aparecida de Goiânia, até 90 dias, voluntária), pedida pelo CAPS AD pela regulação. Precisa de moradia temporária durante o tratamento: o CAPS AD avalia a vaga em Unidade de Acolhimento. Em situação de rua: Centro POP e Consultório na Rua. Comunidade terapêutica: só com entrada voluntária. Prefira as acompanhadas pelo CAPS e pela assistência social. Internação involuntária: só com pedido da família ou do responsável e decisão de um médico, em unidade de saúde, comunicada ao Ministério Público em até 72h (Lei 13.840/2019). Não é o primeiro caminho. Grupos gratuitos de ajuda mútua: Alcoólicos Anônimos e Narcóticos Anônimos; para a família, Al-Anon e Nar-Anon. | G41: Cartão do SUS e documento, se tiver (a falta não impede o atendimento) | I41: credeq, samu, 188 | J41: Ver aba Fontes e docs/levantamento-2026-10-08.md
A42: apostas | B42: Apostas e bets fora de controle | C42: Apostas | D42: Rede de proteção | E42: Bloqueio no gov.br + cuidado no SUS | F42: Bloquear todas as bets de uma vez: Plataforma Centralizada de Autoexclusão (gov.br/autoexclusaoapostas), com conta gov.br prata ou ouro. Vale de 1 a 12 meses ou por tempo indeterminado e corta a publicidade. O bloqueio não pode ser desfeito antes do prazo escolhido (no indeterminado, dá para cancelar em até 30 dias). Ele só alcança as bets autorizadas: sites ilegais continuam abertos. Cuidado em saúde: UBS ou CAPS (em geral o CAPS AD), sem encaminhamento. O Ministério da Saúde também oferece teleatendimento para problemas com apostas pelo app Meu SUS Digital. Pergunte sobre pensamentos de suicídio: dívida e vergonha aumentam o risco. Havendo, siga o manejo da crise e o CVV 188. Proteger o dinheiro: por um tempo, deixar cartão e senhas com alguém de confiança, tirar limites e Pix automático, não pegar empréstimo para cobrir aposta. Dívidas: Procon Goiás (Núcleo de Apoio aos Superendividados) ou Defensoria, para renegociar. Bolsa Família e BPC: desde 2025 as bets autorizadas devem barrar beneficiários (Portaria SPA/MF 2.217/2025). A regra está em discussão no STF; se a pessoa ainda consegue apostar, use a autoexclusão. Menor de 18 anos não pode apostar. Se está apostando, usa conta de adulto ou site ilegal: converse com a família; se um adulto facilita, Conselho Tutelar. Família: o CAPS orienta os familiares. Há grupos gratuitos de Jogadores Anônimos. | G42: Conta gov.br prata ou ouro (para a autoexclusão) Cartão do SUS | I42: autoexclusao, 188, procon, dpe | J42: Ver aba Fontes e docs/levantamento-2026-10-08.md
A43: games | B43: Uso excessivo de jogos eletrônicos e internet | C43: Jogos eletrônicos | D43: Rede de proteção | E43: UBS e CAPS | F43: Primeiro acolhimento na UBS: avaliar sono, humor, ansiedade, isolamento e rendimento na escola ou no trabalho. Prejuízo grave, agressividade ao ser interrompido ou outro sofrimento junto: CAPS, sem encaminhamento (CAPSij até 18 anos). Criança e adolescente: combinar com a família horários e lugar do aparelho, usar o controle parental e manter o celular fora do quarto à noite. Abandono da escola: conversar com a escola; se persistir, Conselho Tutelar. Jogo com dinheiro (caixas de recompensa, apostas em itens, cassino): tratar também como aposta. O ECA Digital (Lei 15.211/2025) proíbe caixas de recompensa em jogos para crianças e adolescentes. Psicoterapia gratuita: clínicas-escola de psicologia (PUC Goiás e UFG). | G43: Cartão do SUS | I43: capsi, puc-cepsi, ufg-psi, anhanguera-psi | J43: Ver aba Fontes e docs/levantamento-2026-10-08.md
A44: discrim | B44: Discriminação: racismo, xenofobia, intolerância religiosa, LGBTfobia | C44: Discriminação | D44: Rede de proteção | E44: É crime: denuncie | F44: Acolher e acreditar no relato. Perguntar se há risco agora (ameaça, ataque ao terreiro, à casa ou à pessoa): se houver, 190. Guardar provas: prints com data, áudios, vídeos, nomes e contatos de testemunhas, local e horário. Registrar ocorrência: Deacri (Goiânia), especializada em crimes raciais e de intolerância, ou em qualquer delegacia. Também pelo 197 (Polícia Civil). Não precisa de advogado. Denúncia, anônima se quiser, pelo Disque 100 (24h, também por WhatsApp). Apoio psicológico, social e jurídico gratuito: Crei, Centro de Referência Estadual da Igualdade (Seds), presencial ou on-line. Reparação e direitos: Defensoria Pública (há o projeto Terreiro de Direitos para comunidades de matriz africana). Casos coletivos, contra escolas, empresas ou órgãos públicos: Ministério Público. No trabalho: Ministério Público do Trabalho. Na escola: direção e, se a vítima for criança ou adolescente, Conselho Tutelar. Em serviço público: ouvidoria do órgão. Pessoa migrante: além da delegacia, a Pastoral dos Migrantes acompanha; a Defensoria Pública da União orienta sobre documentos. Sofrimento depois da violência: UBS, CAPS ou clínicas-escola de psicologia. | G44: Documento com foto, se tiver (migrante: qualquer documento ou protocolo) Provas: prints, áudios, vídeos, testemunhas | I44: deacri, crei, 100, pc197, dpe, mpgo-dh, mpt | J44: Ver aba Fontes e docs/levantamento-2026-10-08.md
A45: r-mental | B45: Cuidado em saúde mental | C45: Saúde mental | D45: Rede de proteção | E45: UBS e CAPS | F45: Risco imediato ou tentativa de suicídio: SAMU 192. Apoio emocional 24h: CVV 188. Primeiro atendimento: UBS do bairro ou CAPS (acesso direto). Crise sem risco de vida: UPA ou CAIS. | G45: Cartão do SUS e documento, se tiver | H45: saude | I45: capsi, puc-cepsi, ufg-psi, anhanguera-psi | J45: Ver aba Fontes e docs/levantamento-2026-10-08.md
A46: r-gest | B46: Pré-natal e parto | C46: Pré-natal | D46: Rede de proteção | E46: SUS | F46: Iniciar o pré-natal na UBS do bairro, de preferência até a 12ª semana. Informar a gestação no CRAS para o adicional do Bolsa Família. Urgência na gravidez ou parto com risco: SAMU 192 ou HMI. | G46: Cartão do SUS Documento com foto | H46: saude | I46: hmi | J46: Ver aba Fontes e docs/levantamento-2026-10-08.md
A47: r-fome | B47: Segurança alimentar | C47: Segurança alimentar | D47: Rede de proteção | E47: CRAS | F47: Procurar o CRAS para benefício eventual (cesta básica) e avaliação da família. Fazer ou atualizar o CadÚnico para Bolsa Família, Mães de Goiás e Gás do Povo. Refeição a R$ 2 no Restaurante do Bem (OVG). Igreja ou ONG que serve refeições pode se cadastrar no Banco de Alimentos da OVG. | G47: Documento com foto e CPF | H47: cras | I47: restbem, bancoalimentos | J47: Ver aba Fontes e docs/levantamento-2026-10-08.md

Sheet Temas
A1: Chave (não altere) | B1: Título | C1: Palavras-chave (sem acento, separadas por vírgula) | D1: Liga a situação do app | E1: Passo a passo (um por linha) | F1: Contatos (IDs da aba Serviços) | G1: Frase de urgência
A2: avc | B2: AVC (derrame) | C2: avc, derrame, boca torta, fala enrolada, nao consegue falar, braco fraco, perdeu a forca, paralisia | E2: Acontecendo agora: ligar 192 (SAMU). O tratamento do AVC depende do tempo, cada minuto conta. Sinais de alerta: boca torta ao sorrir, braço fraco ao levantar os dois, fala enrolada ou confusa. Anotar a hora em que os sintomas começaram e os remédios que a pessoa usa. Não dar comida, bebida nem remédio; se vomitar, deitar a pessoa de lado. AVC que já passou: pedir na UBS o encaminhamento para reabilitação (fisioterapia, fonoaudiologia) e acompanhar pressão, diabetes e remédios na UBS. Novo sinal de AVC a qualquer momento: 192 de novo. | F2: samu, hugo | G2: Se os sinais de AVC estão acontecendo agora (boca torta, braço fraco, fala enrolada): ligue 192 (SAMU) e anote a hora em que começaram.
A3: emergencia | B3: Emergência médica | C3: infarto, dor no peito, falta de ar, desmai, convuls, sangramento, acidente, inconsciente, overdose, engasg, queimadura grave | E3: Risco de vida: ligar 192 (SAMU). O médico regulador orienta pelo telefone e envia a ambulância. Sem risco de vida, mas precisa de atendimento hoje: UPA ou CAIS 24h. Intoxicação ou picada de animal: CIATox 0800 646 4350, 24h. | F3: samu, ciatox | G3: Se há risco de vida agora: ligue 192 (SAMU).
A4: reabilitacao | B4: Reabilitação: fisioterapia, fono, órteses e próteses | C4: reabilita, fisioterap, fisio, pos cirurg, pos-cirurg, sequela, protese, ortese, cadeira de rodas, andador, fonoaudio, terapia ocupacional, amputa, lesao medular | E4: Pedir na UBS, ou ao médico que fez a cirurgia, o encaminhamento para reabilitação, com relatório e exames. A UBS coloca o pedido na regulação. A vaga (fisioterapia, fonoaudiologia, CRER ou clínica-escola) é marcada pela Secretaria de Saúde. Em Goiânia, o CRER é a referência estadual em reabilitação. A primeira consulta vem pela regulação, não por procura direta. Cadeira de rodas, órtese e prótese também são pedidas pela UBS, com prescrição. Pessoa que não consegue sair de casa: perguntar na UBS ou no hospital pelo Melhor em Casa (atendimento no domicílio). Demora longa: guardar o protocolo e procurar a Ouvidoria do SUS (136) ou a Defensoria. | F4: crer, puc-vida, reggyn, 136
A5: acamado | B5: Pessoa acamada ou que depende de cuidados | C5: acamad, cuidador, home care, melhor em casa, curativo em casa, sonda, oxigenio, nao anda, dependente de cuidado | E5: Pedir à UBS a visita da equipe de saúde da família. Atendimento em casa pelo SUS (Melhor em Casa): pedido pela UBS ou pelo hospital, na alta. Fralda geriátrica de graça na Farmácia Popular (60 anos ou mais, ou pessoa com deficiência), com receita. Renda baixa: BPC, se a família tiver até 1/4 do salário mínimo por pessoa. O CRAS orienta. Cuidador sobrecarregado: o CRAS orienta sobre apoio à família. | F5: fp, 121
A6: fila | B6: Consulta, exame ou cirurgia demorando | C6: fila, demora, esperando, aguardando, especialista, ressonancia, tomografia, regulacao, marcar consulta | E6: Confirmar na UBS se o pedido está na regulação e anotar o número do protocolo. Demora sem resposta: Ouvidoria do SUS, 136. Risco à saúde pela demora: Defensoria Pública ou Ministério Público, com laudo e protocolo. | F6: reggyn, 136, dpe, mpgo
A7: familia | B7: Pensão alimentícia, guarda, divórcio, paternidade | C7: pensao aliment, pensao do filho, pensao para, guarda, divorcio, separacao, paternidade, dna, visita dos filhos, uniao estavel, inventario, heranca, curatela, interdicao | E7: Defensoria Pública: atende de graça quem não pode pagar advogado. Acordo sem processo: Cejusc do TJGO (conciliação gratuita sobre pensão, guarda, visitas e divórcio). Levar documentos pessoais, certidões (nascimento dos filhos, casamento) e comprovantes de renda e despesas. Alternativa: escritório-modelo de faculdade de Direito (NPJ PUC Goiás). Se houver violência: medida protetiva na DEAEM ou na Defensoria. | F7: dpe, cejusc, puc-npj
A8: inss | B8: INSS: aposentadoria, auxílio-doença, pensão por morte | C8: inss, aposentad, auxilio doenca, auxilio-doenca, incapacidade, pericia, pensao por morte, auxilio reclusao, salario maternidade | E8: Pedir pelo Meu INSS (app ou site, com a conta gov.br) ou pelo telefone 135. Auxílio por incapacidade: levar laudo e exames à perícia. Negado: recorrer pelo Meu INSS em até 30 dias, ou procurar a Defensoria Pública da União ou o NPJ. BPC (LOAS): veja o assunto Renda e benefícios. | F8: 135, puc-npj
A9: emprego | B9: Desemprego e seguro-desemprego | C9: desempreg, seguro desemprego, seguro-desemprego, emprego, curriculo, demitid, fgts | E9: Seguro-desemprego: pedir pelo app Carteira de Trabalho Digital ou pelo gov.br, do 7º ao 120º dia depois da demissão. Vagas e orientação: Sine Goiânia, com agendamento pelo app Prefeitura 24h. Quer abrir um negócio: veja o assunto Trabalho (Crédito Social). Família sem renda: CRAS, para CadÚnico e benefícios. | F9: sine
A10: dividas | B10: Dívidas, golpes e problemas de consumo | C10: divida, nome sujo, negativad, serasa, juros, emprestimo, consignado, golpe, fraude, cobranca, cartao de credito, superendivid | E10: Procon Goiás: reclamação e renegociação de dívidas (Núcleo de Apoio aos Superendividados). Negociação online: consumidor.gov.br. Golpe ou fraude: registrar boletim de ocorrência e avisar o banco na hora. Desconto indevido na aposentadoria: Meu INSS e Defensoria. | F10: procon, dpe
A11: desastre | B11: Enchente, incêndio ou desabamento | C11: enchente, alagamento, incendio, desabamento, desabrigad, deslizamento, perdeu a casa | E11: Risco agora: Bombeiros 193 ou Defesa Civil 199. Perdeu bens ou a casa: CRAS, para benefício eventual e acolhimento provisório. Documentos perdidos: 2ª via gratuita de certidão (assunto Documentos). | F11: 121 | G11: Risco agora: 193 (Bombeiros) ou 199 (Defesa Civil).
A12: funeral | B12: Morte na família: funeral e luto | C12: funeral, enterro, sepultamento, obito, faleceu, falecimento, luto, morreu | E12: Família de baixa renda: pedir o auxílio funeral (benefício eventual) no CRAS ou na Secretaria de Assistência Social. Certidão de óbito: no cartório, com a declaração de óbito do hospital ou do IML. Pensão por morte: Meu INSS ou 135. Luto difícil: UBS, CAPS ou CVV 188. Se a morte foi por suicídio, ofereça acompanhamento à família. | F12: 121, 188
A13: rg | B13: RG, CPF ou carteira de trabalho | C13: rg, identidade, cpf, carteira de trabalho, titulo de eleitor, documento perdido, documentos perdidos | E13: Carteira de Identidade: agendar no Vapt Vupt (vaptvupt.go.gov.br), levando a certidão de nascimento ou casamento. CPF: de graça pelo site da Receita Federal. Carteira de Trabalho: é digital, pelo app Carteira de Trabalho Digital com a conta gov.br. Sem certidão: 2ª via gratuita (assunto Documentos).
A14: apostas | B14: Apostas e bets | C14: bet, bets, aposta, apostas, apostando, apostador, cassino, tigrinho, jogo do tigre, jogo do bicho, jogos de azar, roleta, aviator | D14: apostas
A15: games | B15: Jogos eletrônicos e internet | C15: videogame, video game, jogos eletronicos, jogo eletronico, games, free fire, roblox, minecraft, fortnite, viciado em jogo, vicio em jogo, viciado no celular, vicio em celular, vicio em internet | D15: games
A16: drogas | B16: Álcool e outras drogas | C16: alcool, bebida, bebe muito, alcoolismo, alcoolatra, droga, drogas, crack, cocaina, maconha, dependencia quimica, dependente quimico, internar, internacao, clinica de recuperacao, comunidade terapeutica | D16: drogas
A17: violsexual | B17: Violência sexual | C17: estupro, estuprad, abuso sexual, abusada, abusado, violencia sexual, assedio sexual, importunacao | E17: Nas primeiras 72h: atendimento de saúde imediato para profilaxia de HIV e IST e contracepção de emergência. Em Goiânia, o Hemu tem ambulatório próprio para vítimas de violência sexual (procura direta ou encaminhamento); também UPA ou CAIS 24h. Registrar ocorrência é um direito, não uma condição para o atendimento de saúde. Mulher: DEAEM (24h). Criança ou adolescente: DPCA e Conselho Tutelar. Gravidez resultante de estupro: a interrupção é prevista em lei. O Hemu é a referência estadual. Acompanhamento psicológico e social: CREAS e, para mulheres, Centro de Referência Cora Coralina. Criança ou adolescente: comunicar sempre ao Conselho Tutelar. | F17: hem, deaem, dpca, cora, 100 | G17: Violência sexual nas últimas 72h: atendimento de saúde agora (profilaxia de HIV e IST e contracepção de emergência), mesmo sem registrar ocorrência.
A18: violidoso | B18: Violência, abandono ou exploração de pessoa idosa ou com deficiência | C18: violencia contra idoso, violencia contra idosa, violencia contra o idoso, violencia contra a idosa, violencia contra pessoa idosa, violencia contra a pessoa idosa, violencia contra pessoa com deficiencia, violencia contra a pessoa com deficiencia, idoso apanha, idosa apanha, avo apanha, avo esta apanhando, avo ta apanhando, bate no idoso, bate na idosa, bate no avo, bate na avo, bateu no avo, bateu na avo, batendo no avo, batendo na avo, agride o idoso, agride a idosa, agrediu o idoso, agrediu a idosa, agressao ao idoso, agressao a idosa, maus tratos ao idoso, maus tratos a idosa, maus tratos contra idoso, maus tratos contra a pessoa idosa, maus tratos a pessoa com deficiencia, idoso sofrendo maus, idosa sofrendo maus, idoso sofrendo violencia, idosa sofrendo violencia, idoso maltratad, idosa maltratad, maltrata o idoso, maltrata a idosa, maltrata o avo, maltrata a avo, idoso abandonad, idosa abandonad, abandono de idoso, abandono do idoso, abandono da idosa, idoso largad, idosa largad, idoso negligenciad, idosa negligenciad, negligencia com idoso, negligencia com o idoso, negligencia com a idosa, idoso trancad, idosa trancad, pega o cartao do aposentad, pegam o cartao do aposentad, toma o cartao do aposentad, fica com o cartao do aposentad, pega a aposentadoria, pegam a aposentadoria, toma a aposentadoria, fica com a aposentadoria, fica com o dinheiro da aposentadoria, fica com o dinheiro do idoso, exploracao financeira, emprestimo no nome do idoso, emprestimo no nome da idosa, emprestimo no nome do avo, emprestimo no nome da avo | D18: violIdoso
A19: discriminacao | B19: Discriminação: racismo, xenofobia, intolerância religiosa, LGBTfobia | C19: racismo, racista, injuria racial, ofensa racial, preconceito, discrimina, xenofob, por ser nordestin, por ser estrangeir, por ser venezuelan, por ser haitian, volta pro seu pais, homofobia, homofob, transfobia, lgbtfobia, intolerancia religiosa, racismo religioso, atacaram o terreiro, ataque ao terreiro, invadiram o terreiro, por ser do candomble, por ser da umbanda, por causa da religiao, por causa da minha religiao, perseguido pela religiao, perseguida pela religiao, por ser evangelic, por ser catolic, por ser espirita, por ser muculman, por ser judeu, por ser judia, macumbeir, chutaram a imagem, capacitismo, capacitista, idadismo, etarismo, xingou de macaco | D19: discrim
A20: trans | B20: Pessoa trans: saúde e documentos | C20: pessoa trans, mulher trans, homem trans, menina trans, menino trans, transexual, travesti, transgenero, hormonizacao, nome social, mudar o nome, redesignacao | E20: Saúde: pedir na UBS o encaminhamento para o Ambulatório TX do HGG (hormonização, psicologia, cirurgias). Maiores de 18 em Goiânia também podem procurar o Transviver. Nome social: pode ser usado no SUS, na escola e no CadÚnico, sem mudar documento. Mudar nome e gênero nos documentos: direto no cartório, sem processo e sem cirurgia, para maiores de 18 anos. Defensoria orienta quem não pode pagar as taxas. Violência ou discriminação: Deacri e Disque 100. | F20: hgg-tx, transviver, deacri, dpe
A21: migrante | B21: Migrantes e refugiados | C21: migrante, imigrante, refugiad, venezuelan, haitian, estrangeir, refugio, sem documento brasileiro | E21: O SUS atende sem exigir documento brasileiro. A criança tem direito à matrícula na escola. CadÚnico e benefícios: pode se cadastrar com a Carteira de Registro Nacional Migratório (CRNM) ou o protocolo de refúgio, no CRAS. Documentos, trabalho e orientação: Pastoral dos Migrantes de Goiânia. Regularização migratória com problema: Defensoria Pública da União. Sofreu xenofobia: é crime (Lei 7.716/1989). Registrar na Deacri ou em qualquer delegacia, ou pelo Disque 100. | F21: pastoral-migrantes, deacri, 100, 121
A22: egresso | B22: Saiu do sistema prisional (egresso) e família | C22: egresso, saiu da prisao, saiu da cadeia, ex-detento, ex detento, presidiario, tornozeleira, liberdade condicional, foi preso, esta preso, presidio | E22: Escritório Social (Goiânia): documentos, trabalho, estudo e acesso a políticas sociais para egressos e famílias. Atendimento voluntário. Família de pessoa presa: auxílio-reclusão no INSS, se a pessoa contribuía (Meu INSS ou 135). CadÚnico e benefícios no CRAS; situação de rua: Centro POP. Dúvidas sobre a pena ou o processo: Defensoria Pública. | F22: escritorio-social, dpe, 135
A23: cancer | B23: Câncer: diagnóstico e tratamento | C23: cancer, tumor, quimioterapia, radioterapia, oncolog, biopsia, nodulo, metastase | E23: Pela lei, exames para confirmar câncer devem sair em até 30 dias (Lei 13.896/2019) e o tratamento no SUS deve começar em até 60 dias do diagnóstico (Lei 12.732/2012). O encaminhamento sai da UBS ou do médico, pela regulação. Em Goiânia, a referência é o Hospital Araújo Jorge; também o HC-UFG. Demora: guardar laudos e protocolos e procurar a Ouvidoria do SUS (136), a Defensoria ou o Ministério Público. Direitos: saque do FGTS e do PIS, auxílio por incapacidade no INSS, isenção de IR sobre aposentadoria; BPC se a renda for baixa. Transporte e hospedagem para quem vem do interior: pedir o Tratamento Fora de Domicílio (TFD) na Secretaria de Saúde do município. | F23: araujo-jorge, hc-ufg, 136, dpe
A24: trafico | B24: Tráfico de pessoas e trabalho escravo | C24: trafico de pessoas, trabalho escravo, escravidao, proposta de emprego no exterior, retiveram o passaporte, sem salario, nao deixam sair | E24: Risco agora: 190. Denunciar pelo Disque 100 (24h, também pelo WhatsApp (61) 99611-0100) ou pelo Ligue 180. As denúncias de trabalho escravo seguem para a fiscalização do Ministério do Trabalho. Trabalho análogo à escravidão: Ministério Público do Trabalho e Sistema Ipê do Ministério do Trabalho. Proposta de emprego no exterior boa demais, com passagem paga e documento retido: sinal de alerta. | F24: 100, 180, mpt
A25: dentista | B25: Dentista | C25: dente, dentista, odonto, dentadura, protese dentaria | E25: Primeira consulta na UBS, com a equipe de saúde bucal. Tratamento especializado (canal, prótese, cirurgia): a UBS encaminha ao Centro de Especialidades Odontológicas (CEO). Dor forte ou rosto inchado: UPA ou CAIS 24h.

Sheet Registros
A1: ID | B1: Dia | C1: Hora | D1: Município | E1: Região de Goiânia | F1: Gênero | G1: Faixa de idade | H1: Pessoas na casa | I1: Renda por pessoa | J1: Trabalho | K1: Moradia | L1: Escolaridade | M1: Assuntos | N1: Situações | O1: Políticas indicadas | P1: Lugares do roteiro | Q1: Temas do pedido livre | R1: Pedido sem orientação | S1: Urgência | T1: Respostas que faltaram

Sheet Resumo
A1: Resumo dos atendimentos registrados
A2: Contagens por fórmula sobre a aba Registros. Listas separadas por ponto e vírgula são contadas pelo nome.
A4: Indicador | B4: Valor
A5: Atendimentos registrados | B5: =COUNTA(Registros!A2:A)
A6: Com urgência | B6: =COUNTIF(Registros!S2:S,"Sim")
A7: Com urgência (%) | B7: =IF(B5=0,0,B6/B5)
A8: Renda até R$ 218 por pessoa | B8: =COUNTIF(Registros!I2:I,"Sem renda")+COUNTIF(Registros!I2:I,"Até R$ 109")+COUNTIF(Registros!I2:I,"De R$ 110 a R$ 218")
A9: Renda até R$ 218 por pessoa (%) | B9: =IF(B5=0,0,B8/B5)
A10: Pedidos livres sem orientação pronta | B10: =COUNTIF(Registros!R2:R,"Sim")
A11: Serviços que precisam de conferência | B11: =COUNTIF('Serviços'!P2:P,"Sim")
A13: Assuntos | B13: Atendimentos | C13: % do total
A14: Renda e benefícios | B14: =COUNTIF(Registros!$M$2:$M,"*"&$A14&"*") | C14: =IF($B$5=0,0,B14/$B$5)
A15: Comida | B15: =COUNTIF(Registros!$M$2:$M,"*"&$A15&"*") | C15: =IF($B$5=0,0,B15/$B$5)
A16: Moradia | B16: =COUNTIF(Registros!$M$2:$M,"*"&$A16&"*") | C16: =IF($B$5=0,0,B16/$B$5)
A17: Saúde e remédios | B17: =COUNTIF(Registros!$M$2:$M,"*"&$A17&"*") | C17: =IF($B$5=0,0,B17/$B$5)
A18: Saúde mental e dependências | B18: =COUNTIF(Registros!$M$2:$M,"*"&$A18&"*") | C18: =IF($B$5=0,0,B18/$B$5)
A19: Violência e proteção | B19: =COUNTIF(Registros!$M$2:$M,"*"&$A19&"*") | C19: =IF($B$5=0,0,B19/$B$5)
A20: Educação | B20: =COUNTIF(Registros!$M$2:$M,"*"&$A20&"*") | C20: =IF($B$5=0,0,B20/$B$5)
A21: Trabalho | B21: =COUNTIF(Registros!$M$2:$M,"*"&$A21&"*") | C21: =IF($B$5=0,0,B21/$B$5)
A22: Documentos | B22: =COUNTIF(Registros!$M$2:$M,"*"&$A22&"*") | C22: =IF($B$5=0,0,B22/$B$5)
A23: Direito negado | B23: =COUNTIF(Registros!$M$2:$M,"*"&$A23&"*") | C23: =IF($B$5=0,0,B23/$B$5)
A25: Renda por pessoa | B25: Atendimentos | C25: % do total
A26: Sem renda | B26: =COUNTIF(Registros!$I$2:$I,$A26) | C26: =IF($B$5=0,0,B26/$B$5)
A27: Até R$ 109 | B27: =COUNTIF(Registros!$I$2:$I,$A27) | C27: =IF($B$5=0,0,B27/$B$5)
A28: De R$ 110 a R$ 218 | B28: =COUNTIF(Registros!$I$2:$I,$A28) | C28: =IF($B$5=0,0,B28/$B$5)
A29: Até 1/4 do salário | B29: =COUNTIF(Registros!$I$2:$I,$A29) | C29: =IF($B$5=0,0,B29/$B$5)
A30: Até 1/2 salário | B30: =COUNTIF(Registros!$I$2:$I,$A30) | C30: =IF($B$5=0,0,B30/$B$5)
A31: Até 1 salário | B31: =COUNTIF(Registros!$I$2:$I,$A31) | C31: =IF($B$5=0,0,B31/$B$5)
A32: Até 3 salários | B32: =COUNTIF(Registros!$I$2:$I,$A32) | C32: =IF($B$5=0,0,B32/$B$5)
A33: Mais de 3 salários | B33: =COUNTIF(Registros!$I$2:$I,$A33) | C33: =IF($B$5=0,0,B33/$B$5)
A34: Não informada | B34: =COUNTIF(Registros!$I$2:$I,$A34) | C34: =IF($B$5=0,0,B34/$B$5)
A36: Faixa de idade | B36: Atendimentos | C36: % do total
A37: Até 13 | B37: =COUNTIF(Registros!$G$2:$G,$A37) | C37: =IF($B$5=0,0,B37/$B$5)
A38: 14 a 15 | B38: =COUNTIF(Registros!$G$2:$G,$A38) | C38: =IF($B$5=0,0,B38/$B$5)
A39: 16 a 17 | B39: =COUNTIF(Registros!$G$2:$G,$A39) | C39: =IF($B$5=0,0,B39/$B$5)
A40: 18 a 29 | B40: =COUNTIF(Registros!$G$2:$G,$A40) | C40: =IF($B$5=0,0,B40/$B$5)
A41: 30 a 59 | B41: =COUNTIF(Registros!$G$2:$G,$A41) | C41: =IF($B$5=0,0,B41/$B$5)
A42: 60 a 64 | B42: =COUNTIF(Registros!$G$2:$G,$A42) | C42: =IF($B$5=0,0,B42/$B$5)
A43: 65 ou mais | B43: =COUNTIF(Registros!$G$2:$G,$A43) | C43: =IF($B$5=0,0,B43/$B$5)
A44: Não informada | B44: =COUNTIF(Registros!$G$2:$G,$A44) | C44: =IF($B$5=0,0,B44/$B$5)
A46: Município | B46: Atendimentos | C46: % do total
A47: Goiânia | B47: =COUNTIF(Registros!$D$2:$D,$A47) | C47: =IF($B$5=0,0,B47/$B$5)
A48: Aparecida de Goiânia | B48: =COUNTIF(Registros!$D$2:$D,$A48) | C48: =IF($B$5=0,0,B48/$B$5)
A49: Senador Canedo | B49: =COUNTIF(Registros!$D$2:$D,$A49) | C49: =IF($B$5=0,0,B49/$B$5)
A50: Trindade | B50: =COUNTIF(Registros!$D$2:$D,$A50) | C50: =IF($B$5=0,0,B50/$B$5)
A51: Goianira | B51: =COUNTIF(Registros!$D$2:$D,$A51) | C51: =IF($B$5=0,0,B51/$B$5)
A52: Abadia de Goiás | B52: =COUNTIF(Registros!$D$2:$D,$A52) | C52: =IF($B$5=0,0,B52/$B$5)
A53: Aragoiânia | B53: =COUNTIF(Registros!$D$2:$D,$A53) | C53: =IF($B$5=0,0,B53/$B$5)
A54: Bela Vista de Goiás | B54: =COUNTIF(Registros!$D$2:$D,$A54) | C54: =IF($B$5=0,0,B54/$B$5)
A55: Bonfinópolis | B55: =COUNTIF(Registros!$D$2:$D,$A55) | C55: =IF($B$5=0,0,B55/$B$5)
A56: Brazabrantes | B56: =COUNTIF(Registros!$D$2:$D,$A56) | C56: =IF($B$5=0,0,B56/$B$5)
A57: Caldazinha | B57: =COUNTIF(Registros!$D$2:$D,$A57) | C57: =IF($B$5=0,0,B57/$B$5)
A58: Caturaí | B58: =COUNTIF(Registros!$D$2:$D,$A58) | C58: =IF($B$5=0,0,B58/$B$5)
... A66: Terezópolis de Goiás | B66: =COUNTIF(Registros!$D$2:$D,$A66) | C66: =IF($B$5=0,0,B66/$B$5)

Sheet Fontes
A1: Escrito em | B1: Fonte | C1: Objeto | D1: Obtido por | E1: Pedido | F1: Parâmetros | G1: Data | H1: Pedido por | I1: Linhas | J1: Mudanças depois de obter | K1: Observações
A2: Serviços!A1:P127 | B2: Encaminha Goiânia, index.html (commit aead8b5) | C2: lista S (serviços e contatos) | D2: Exportado por Claude do código do app | E2: Criar banco de dados independente no Google Planilhas | G2: 08/10/2026 | I2: 126 | J2: Fonte e data extraídas da observação quando havia | K2: Contatos vêm do protótipo e do levantamento de 08/10/2026 (docs/levantamento-2026-10-08.md).
A3: Políticas!A1:L47 | B3: Encaminha Goiânia, index.html (commit aead8b5) | C3: lista P (políticas) | D3: Exportado por Claude do código do app | E3: Criar banco de dados independente no Google Planilhas | G3: 08/10/2026 | I3: 46 | J3: Critérios de direito não exportados (ficam no código)
A4: Temas!A1:G25 | B4: Encaminha Goiânia, index.html (commit aead8b5) | C4: lista TEMAS (pedido livre) | D4: Exportado por Claude do código do app | E4: Criar banco de dados independente no Google Planilhas | G4: 08/10/2026 | I4: 24 | J4: Marcação HTML retirada da frase de urgência
